{"555": {"name": ["Laurentius Praktijkschool"], "brinnr": "26mj", "rad": 5, "selected": "false", "loc": [52.0126494, 4.3433804]}, "274": {"name": ["Maaslandcollege Scholengemeenschap voor Mavo Havo Vwo"], "brinnr": "20wi", "rad": 5, "selected": "false", "loc": [51.7625622, 5.5232898]}, "470": {"name": ["Christelijk College Griftland School voor Atheneum Havo en Mavo"], "brinnr": "01nz", "rad": 5, "selected": "false", "loc": [52.1919347, 5.2896721]}, "424": {"name": ["Pius X College Scholengemeenschap voor Lyceum Havo Mavo Vbo Lwoo"], "brinnr": "02ek", "rad": 5, "selected": "false", "loc": [52.3621966, 6.6424677]}, "131": {"name": ["Van Lodenstein College Reformatorische School voor Praktijkonderwijs"], "brinnr": "26mv", "rad": 5, "selected": "false", "loc": [52.0264883, 5.6546533]}, "295": {"name": ["Scholengemeenschap Breda voor Katholiek Lyceum Havo Mavo Vbo Lwoo"], "brinnr": "25gc", "rad": 5, "selected": "false", "loc": [51.59081639999999, 4.749850299999999]}, "87": {"name": ["Rooms Katholieke Scholengemeenschap Marianum voor Lyc Havo Mavo Vbo Lwoo"], "brinnr": "02qn", "rad": 5, "selected": "false", "loc": [52.0394298, 6.614200899999999]}, "195": {"name": ["Emmacollege voor Havo Mavo Vbo Lwoo"], "brinnr": "05fj", "rad": 5, "selected": "false", "loc": [50.92926130000001, 5.955558]}, "607": {"name": ["Openbare Scholengemeenschap Nieuw Zuid voor Lyceum Havo Mavo Vbo Lwoo"], "brinnr": "02lb", "rad": 5, "selected": "false", "loc": [51.897411, 4.508227]}, "433": {"name": ["Reggesteyn Christelijke Scholengemeenschap voor Pro-Vmbo-Havo-Atheneum-Gymnasiu"], "brinnr": "02xj", "rad": 5, "selected": "false", "loc": [52.3552304, 6.4614415]}, "169": {"name": ["Heyerdahl College Openbare School voor Praktijkonderwijs"], "brinnr": "17sg", "rad": 5, "selected": "false", "loc": [53.2362772, 6.6070837]}, "261": {"name": ["OMO Scholengroep De Langstraat"], "brinnr": "16vk", "rad": 5, "selected": "false", "loc": [51.6862894, 5.0807163]}, "200": {"name": ["Stella Maris College voor Lyc Havo Mavo Vbo Lwoo"], "brinnr": "20is", "rad": 5, "selected": "false", "loc": [50.882096, 5.755168599999999]}, "309": {"name": ["Openbare Scholengemeensschap Texel voor Ath Havo Mavo Vbo Lwoo"], "brinnr": "16kp", "rad": 5, "selected": "false", "loc": [53.0486792, 4.8016534]}, "428": {"name": ["Bonhoeffer College voor Gymnasium, Atheneum, Havo, VMBO, LWOO en PrO"], "brinnr": "17vn", "rad": 5, "selected": "false", "loc": [52.19045020000001, 6.865264]}, "560": {"name": ["Nova College"], "brinnr": "23yu", "rad": 5, "selected": "false", "loc": [51.8843537, 4.5514437]}, "452": {"name": ["Minkema College voor Lwoo Vmbo Havo Atheneum Gymnasium"], "brinnr": "17an", "rad": 5, "selected": "false", "loc": [52.0841489, 4.8965534]}, "37": {"name": ["Praktijkonderwijs Almere-Bachweg"], "brinnr": "17ji", "rad": 5, "selected": "false", "loc": [52.3695196, 5.1999907]}, "372": {"name": ["School voor Praktische Vorming Oost-ter-Hout"], "brinnr": "15ne", "rad": 5, "selected": "false", "loc": [52.3673997, 4.6337798]}, "548": {"name": ["Oranje Nassau College Scholengemeenschap Ath Havo Mavo Vbo Lwoo"], "brinnr": "20bc", "rad": 5, "selected": "false", "loc": [52.0658758, 4.5119729]}, "360": {"name": ["H Wesselink College Christelijke Scholengemeenschap voor Vwo Havo Mavo"], "brinnr": "02te", "rad": 5, "selected": "false", "loc": [52.2869358, 4.8519076]}, "407": {"name": ["Sancta Maria Lyceum voor Havo, Atheneum en Gymnasium"], "brinnr": "02sb", "rad": 5, "selected": "false", "loc": [52.3659307, 4.6175102]}, "565": {"name": ["Het Waterland"], "brinnr": "09vs", "rad": 5, "selected": "false", "loc": [52.1705129, 4.4847946]}, "34": {"name": ["Scholengemeenschap De Rietlanden Ath Havo Mavo Vbo Lwoo"], "brinnr": "18gc", "rad": 5, "selected": "false", "loc": [52.4979467, 5.475812299999999]}, "556": {"name": ["Unie Noord"], "brinnr": "02vg", "rad": 5, "selected": "false", "loc": [51.9056062, 4.4578374]}, "42": {"name": ["Burg Walda Scholengemeenschap voor VMBO"], "brinnr": "19hy", "rad": 5, "selected": "false", "loc": [53.4459174, 5.763995899999999]}, "247": {"name": ["Voortgezet Onderwijs Best-Oirschot"], "brinnr": "16rt", "rad": 5, "selected": "false", "loc": [51.5014299, 5.388122099999999]}, "373": {"name": ["Praktijkschool De Linie"], "brinnr": "16pj", "rad": 5, "selected": "false", "loc": [52.3192748, 4.7119813]}, "294": {"name": ["Onze Lieve Vrouwelyceum - Breda"], "brinnr": "16rf", "rad": 5, "selected": "false", "loc": [51.5823546, 4.7849425]}, "564": {"name": ["de Passie Evangelische School voor Vmbo-tl, Havo, Atheneum, Gymnasium"], "brinnr": "27rw", "rad": 5, "selected": "false", "loc": [51.9018612, 4.4842992]}, "558": {"name": ["Roncalli MAVO"], "brinnr": "17ky", "rad": 5, "selected": "false", "loc": [51.9365, 4.5555903]}, "356": {"name": ["Scholengemeenschap Reigersbos Atheneum Havo Mavo Leao"], "brinnr": "21ff", "rad": 5, "selected": "false", "loc": [52.2967127, 4.9774075]}, "290": {"name": ["Openbaar Stedelijk College Eindhoven voor Atheneum Havo Mavo Vbo Lwoo"], "brinnr": "20bk", "rad": 5, "selected": "false", "loc": [51.4829721, 5.4858268]}, "443": {"name": ["Openbare Scholengemeenschap Het Stedelijk Lyceum Havo Mavo Vbo Lwoo"], "brinnr": "00ah", "rad": 5, "selected": "false", "loc": [52.233438, 6.885094199999999]}, "171": {"name": ["H. N. Werkman College voor Ath Havo en Mavo"], "brinnr": "20em", "rad": 5, "selected": "false", "loc": [53.22047329999999, 6.5732671]}, "85": {"name": ["Rooms Katholieke Scholengemeenschap Veluws College voor Lyceum Havo Mavo en Vbo"], "brinnr": "02ra", "rad": 5, "selected": "false", "loc": [52.2136697, 5.9392808]}, "263": {"name": ["Van Maerlant voor Mavo Vbo Lwoo"], "brinnr": "17kf", "rad": 5, "selected": "false", "loc": [51.68853980000001, 5.2874591]}, "312": {"name": ["Stedelijk Gymnasium"], "brinnr": "20qy", "rad": 5, "selected": "false", "loc": [52.3815555, 4.6339163]}, "268": {"name": ["Mill-Hillcollege"], "brinnr": "20bq", "rad": 5, "selected": "false", "loc": [51.5290793, 5.0589545]}, "536": {"name": ["DevelsteinCollege Christelijke Scholengemeenschap voor Voortgezet Onderwijs"], "brinnr": "14rr", "rad": 5, "selected": "false", "loc": [51.81744519999999, 4.6268951]}, "138": {"name": ["Pallas Athene College Openbare Scholengemeenschap voor Vwo Havo Mavo Vbo"], "brinnr": "19kz", "rad": 5, "selected": "false", "loc": [52.0374813, 5.6396114]}, "346": {"name": ["Bonhoeffer College Scholengemeenschap voor Mavo Havo Vwo"], "brinnr": "00zd", "rad": 5, "selected": "false", "loc": [52.5432421, 4.6665456]}, "496": {"name": ["Herman Jordanlyceum voor Gymnasium Atheneum en Havo Top"], "brinnr": "02th", "rad": 5, "selected": "false", "loc": [52.0983399, 5.213422599999999]}, "100": {"name": ["De Tender School voor Praktijkonderwijs"], "brinnr": "26nh", "rad": 5, "selected": "false", "loc": [52.0545494, 6.0943181]}, "165": {"name": ["School voor Praktijkonderwijs De Flint"], "brinnr": "19ur", "rad": 5, "selected": "false", "loc": [53.1534233, 7.0346451]}, "188": {"name": ["Bisschop College Broekhin voor Lyceum Havo Mavo Vbo"], "brinnr": "14ps", "rad": 5, "selected": "false", "loc": [51.20769869999999, 6.0114327]}, "74": {"name": ["Candea College Atheneum Havo Mavo Vbo"], "brinnr": "03rr", "rad": 5, "selected": "false", "loc": [51.9471383, 6.0031265]}, "650": {"name": ["Vrije School Zuid-Holland voor Atheneum Havo Mavo"], "brinnr": "16tv", "rad": 5, "selected": "false", "loc": [52.1028751, 4.3152342]}, "257": {"name": ["Sgm Roncalli Samenw Sch RK PC voor Ath Havo Mavo"], "brinnr": "14sw", "rad": 5, "selected": "false", "loc": [51.50218109999999, 4.2856099]}, "55": {"name": ["Christelijke Scholengemeenschap Liudger voor Lyceum Havo Mavo Vbo Lwoo Pro"], "brinnr": "25cm", "rad": 5, "selected": "false", "loc": [53.1041495, 6.115250899999999]}, "110": {"name": ["Nijmeegse Scholengemeenschap Groenewoud voor Vwo Havo en Mavo"], "brinnr": "02ve", "rad": 5, "selected": "false", "loc": [51.8295606, 5.8683293]}, "353": {"name": ["Rooms Katholieke Scholengemeenschap Thamen voor Mavo Vbo Lwoo"], "brinnr": "05fe", "rad": 5, "selected": "false", "loc": [52.2424178, 4.819367]}, "403": {"name": ["Petrus Canisius Colleg Scholengemeenschap voor Lyceum Havo Mavo Vbo Lwoo"], "brinnr": "02qx", "rad": 5, "selected": "false", "loc": [52.6254103, 4.7445523]}, "63": {"name": ["Stellingwerf College"], "brinnr": "15vq", "rad": 5, "selected": "false", "loc": [52.99166530000001, 6.289337799999999]}, "485": {"name": ["Scholengemeenschap Maarsbergen voor Mavo Vbo"], "brinnr": "07kp", "rad": 5, "selected": "false", "loc": [52.05083029999999, 5.402185800000001]}, "102": {"name": ["RSG Lingecollege"], "brinnr": "23hc", "rad": 5, "selected": "false", "loc": [51.8800372, 5.420702599999999]}, "152": {"name": ["Notre Dame Des Anges Havo"], "brinnr": "02qq", "rad": 5, "selected": "false", "loc": [51.835679, 5.9068118]}, "233": {"name": ["Christiaan Huygens College voor Lyceum Havo Mavo Vbo Lwoo"], "brinnr": "02tc", "rad": 5, "selected": "false", "loc": [51.4294236, 5.455006699999999]}, "166": {"name": ["Dollard College voor Lyc Havo Mavo Vbo Lwoo"], "brinnr": "20cm", "rad": 5, "selected": "false", "loc": [53.1466644, 7.038846599999999]}, "65": {"name": ["Vakcollege Sevenwolden"], "brinnr": "05ac", "rad": 5, "selected": "false", "loc": [52.950267, 5.9243134]}, "539": {"name": ["Lentiz onderwijsgroep"], "brinnr": "17wq", "rad": 5, "selected": "false", "loc": [51.9160423, 4.3579968]}, "228": {"name": ["Stedelijk Gymnasium"], "brinnr": "03am", "rad": 5, "selected": "false", "loc": [51.5909887, 4.788842799999999]}, "283": {"name": ["Jan van Brabant College vestiging Deltaweg"], "brinnr": "00ne", "rad": 5, "selected": "false", "loc": [51.47160179999999, 5.6999357]}, "150": {"name": ["Scholengemeenschap van de Capellen voor ATH HAVO MAVO VBO LWOO"], "brinnr": "17bz", "rad": 5, "selected": "false", "loc": [52.4481556, 5.844284099999999]}, "605": {"name": ["MY college voor VMBO"], "brinnr": "23ap", "rad": 5, "selected": "false", "loc": [51.848847, 4.314521099999999]}, "258": {"name": ["Sondervick College RK Scholengemeenschap voor Lyceum Havo Mavo Vbo Lwoo"], "brinnr": "15bs", "rad": 5, "selected": "false", "loc": [51.3982853, 5.3744931]}, "641": {"name": ["Protestants Christelijke School voor Praktijkonderwijs De Poort"], "brinnr": "07mz", "rad": 5, "selected": "false", "loc": [52.0838796, 4.2794604]}, "320": {"name": ["Stedelijk Dalton College Alkmaar voor vwo havo mavo en vbo"], "brinnr": "19zq", "rad": 5, "selected": "false", "loc": [52.6588668, 4.757306199999999]}, "71": {"name": ["Tjalling Koopmans College voor Vwo en Mavo"], "brinnr": "30uv", "rad": 5, "selected": "false", "loc": [53.2151377, 5.9489318]}, "230": {"name": ["Prisma VO"], "brinnr": "19xv", "rad": 5, "selected": "false", "loc": [51.5811449, 4.7523161]}, "438": {"name": ["de Passie, Evangelische school voor Vmbo-tl, Havo, Vwo"], "brinnr": "29wg", "rad": 5, "selected": "false", "loc": [52.35290329999999, 6.5901044]}, "647": {"name": ["Rooms Katholiek Alfrink College Scholengemeenschap voor Atheneum en Havo"], "brinnr": "01mb", "rad": 5, "selected": "false", "loc": [52.0725794, 4.5028312]}, "32": {"name": ["Interconfessionele Scholengemeenschap Arcus voor Atheneum Havo Mavo Vbo Lwoo"], "brinnr": "00zo", "rad": 5, "selected": "false", "loc": [52.5086499, 5.481271]}, "167": {"name": ["Regionale Scholengemeenschap Ter Apel voor Ath Havo Mavo Lhno"], "brinnr": "16ih", "rad": 5, "selected": "false", "loc": [52.8758721, 7.0668319]}, "83": {"name": ["Openbare Regionale Scholengemeenschap Lek en Linge voor atheneum havo vmbo lwoo"], "brinnr": "19ew", "rad": 5, "selected": "false", "loc": [51.9451095, 5.2347144]}, "571": {"name": ["Maris College voor Mavo Vmbo Lwoo"], "brinnr": "19zp", "rad": 5, "selected": "false", "loc": [52.0640685, 4.2480884]}, "225": {"name": ["Onderwijsgroep Tilburg VMBO Reeshof, VMBO LWOO"], "brinnr": "09vg", "rad": 5, "selected": "false", "loc": [51.5732173, 4.9942142]}, "0": {"name": ["School voor Praktijkonderwijs Assen"], "brinnr": "18br", "rad": 5, "selected": "false", "loc": [53.0084124, 6.5522869]}, "350": {"name": ["Katholiek Scholengemeenschap Hoofddorp voor Lyceum HAVO en MAVO"], "brinnr": "00ip", "rad": 5, "selected": "false", "loc": [52.3045662, 4.6653399]}, "643": {"name": ["S. Adelbert College voor Lyceum Havo en Mavo"], "brinnr": "14we", "rad": 5, "selected": "false", "loc": [52.14424899999999, 4.416714]}, "159": {"name": ["Willem Lodewijkgymnasium"], "brinnr": "02cr", "rad": 5, "selected": "false", "loc": [53.2080972, 6.554568499999999]}, "307": {"name": ["Rooms Katholieke Scholengemeenschap METAMEER voor ATH HAVO VMBO LWOO"], "brinnr": "16sw", "rad": 5, "selected": "false", "loc": [51.5958978, 5.922802799999999]}, "531": {"name": ["Scholengroep Esloo PC RK Scholengemeenschap voor Lyceum Havo Mavo Vbo Lwoo"], "brinnr": "21gu", "rad": 5, "selected": "false", "loc": [52.08486449999999, 4.3097046]}, "479": {"name": ["Christelijke Scholengemeenschap voor VMBO en Praktijkonderwijs"], "brinnr": "02mf", "rad": 5, "selected": "false", "loc": [52.0263571, 5.5436185]}, "303": {"name": ["Praktijkschool Helmond"], "brinnr": "26jb", "rad": 5, "selected": "false", "loc": [51.4825884, 5.6793492]}, "196": {"name": ["Sint-Janscollege voor Vwo Havo"], "brinnr": "16sl", "rad": 5, "selected": "false", "loc": [50.9322727, 5.9284478]}, "133": {"name": ["Gymnasium Apeldoorn"], "brinnr": "20qu", "rad": 5, "selected": "false", "loc": [52.2205005, 5.9655036]}, "552": {"name": ["Limes Praktijkonderwijs"], "brinnr": "26hn", "rad": 5, "selected": "false", "loc": [52.1967651, 4.4166668]}, "325": {"name": ["Joodse Scholengemeenschap Maimonides voor Ath Mavo En Afd Havo"], "brinnr": "16pn", "rad": 5, "selected": "false", "loc": [52.3260921, 4.8865383]}, "279": {"name": ["Kwadrant Scholengroep  RK Regionale Scholengemeenschap voor Vwo Havo en Vmbo"], "brinnr": "21gz", "rad": 5, "selected": "false", "loc": [51.6293044, 4.9429166]}, "69": {"name": ["De Praktijkschool"], "brinnr": "26mg", "rad": 5, "selected": "false", "loc": [53.0336837, 5.6417823]}, "406": {"name": ["Don Bosco College Atheneum Havo Vmbo Lwoo"], "brinnr": "20gs", "rad": 5, "selected": "false", "loc": [52.4942488, 5.056429899999999]}, "401": {"name": ["Martinus College Christelijke Scholengemeenschap voor LYC HAVO MAVO VBO LWOO"], "brinnr": "18cv", "rad": 5, "selected": "false", "loc": [52.69196789999999, 5.2194158]}, "14": {"name": ["Openbare Scholengemeenschap voor Lyceum Havo Mavo Vbo Lwoo Esdal College"], "brinnr": "20la", "rad": 5, "selected": "false", "loc": [52.7845907, 6.906085]}, "358": {"name": ["Scholengemeenschap voor Vwo Havo Mavo Het Hervormd Lyceum"], "brinnr": "01tc", "rad": 5, "selected": "false", "loc": [52.3626782, 4.827365299999999]}, "280": {"name": ["Bossche Vakschool voor Mavo Vbo Lwoo"], "brinnr": "23fy", "rad": 5, "selected": "false", "loc": [51.7038498, 5.3258025]}, "205": {"name": ["School voor Speciaal Voortgezet Onderwijs Terra Nigra"], "brinnr": "26hl", "rad": 5, "selected": "false", "loc": [50.8516938, 5.6610115]}, "593": {"name": ["Scala College voor Atheneum Havo Vmbo-Loot"], "brinnr": "10an", "rad": 5, "selected": "false", "loc": [52.1379438, 4.6704269]}, "154": {"name": ["Marnix College  Scholengemeenschap voor Gymnasium Atheneum Havo Mavo"], "brinnr": "02up", "rad": 5, "selected": "false", "loc": [52.0310764, 5.6623098]}, "139": {"name": ["Christelijk College Schaersvoorde voor Atheneum Havo Mavo Vbo Lwoo"], "brinnr": "00lj", "rad": 5, "selected": "false", "loc": [51.9250211, 6.5742695]}, "111": {"name": ["Maaswaal College voor Gymnasium Atheneum Havo Vmbo Lwoo"], "brinnr": "00ob", "rad": 5, "selected": "false", "loc": [51.8061361, 5.75428]}, "553": {"name": ["Edudelta College Middelharnis locatie Schoolstraat afd. Techniek en Economie"], "brinnr": "02ic", "rad": 5, "selected": "false", "loc": [51.7593442, 4.1620344]}, "53": {"name": ["Bogerman Scholengemeenschap voor Lyceum Havo Mavo Vbo Lwoo"], "brinnr": "25cr", "rad": 5, "selected": "false", "loc": [53.0322001, 5.645537099999999]}, "260": {"name": ["Jacob Roelandslyceum"], "brinnr": "16rb", "rad": 5, "selected": "false", "loc": [51.5856953, 5.328233099999999]}, "189": {"name": ["Connect College"], "brinnr": "16pe", "rad": 5, "selected": "false", "loc": [51.1117699, 5.8711787]}, "617": {"name": ["Da Vinci College Openbare Scholengemeenschap voor ATH HAVO MAVO VBO LWOO"], "brinnr": "20df", "rad": 5, "selected": "false", "loc": [52.17234140000001, 4.4825611]}, "49": {"name": ["Lauwers College Christelijk Scholengemeenschap voor Atheneum Havo Mavo Vbo"], "brinnr": "00zv", "rad": 5, "selected": "false", "loc": [53.2498324, 6.153383199999999]}, "527": {"name": ["Christelijk College De Populier"], "brinnr": "02gj", "rad": 5, "selected": "false", "loc": [52.0801635, 4.271552]}, "208": {"name": ["Bonnefantencollege"], "brinnr": "27zj", "rad": 5, "selected": "false", "loc": [50.8505861, 5.6644052]}, "473": {"name": ["Joh van Oldenbarnevelt Gymnasium"], "brinnr": "20ck", "rad": 5, "selected": "false", "loc": [52.1513599, 5.3684718]}, "506": {"name": ["Zwin College Scholengemeenschap voor Vmbo Havo Atheneum Gymnasium"], "brinnr": "00aq", "rad": 5, "selected": "false", "loc": [51.3155964, 3.4698371]}, "357": {"name": ["Wellantcollege"], "brinnr": "01oe", "rad": 5, "selected": "false", "loc": [52.2641248, 4.7699782]}, "380": {"name": ["Praktijkschool Uithoorn"], "brinnr": "26je", "rad": 5, "selected": "false", "loc": [52.24859739999999, 4.817506499999999]}, "206": {"name": ["Porta Mosana College"], "brinnr": "27vg", "rad": 5, "selected": "false", "loc": [50.8290929, 5.7309053]}, "54": {"name": ["Marne College voor Atheneum Havo Mavo Vbo Lwoo"], "brinnr": "25gb", "rad": 5, "selected": "false", "loc": [53.0665852, 5.518364900000001]}, "84": {"name": ["Vrije school Zutphen-Groningen"], "brinnr": "16nk", "rad": 5, "selected": "false", "loc": [52.1260302, 6.196047800000001]}, "549": {"name": ["Chr Scholengemeenschap Groene Hart"], "brinnr": "15bh", "rad": 5, "selected": "false", "loc": [52.1323813, 4.6510923]}, "394": {"name": ["Scholengemeenschap ZAAM Noord voor Vwo Havo Mavo Vbo Lwoo"], "brinnr": "17vf", "rad": 5, "selected": "false", "loc": [52.39472749999999, 4.9305745]}, "23": {"name": ["Oostvaarders College voor Lyceum Havo Mavo Vbo Lwoo"], "brinnr": "24rw", "rad": 5, "selected": "false", "loc": [52.3950922, 5.266564199999999]}, "482": {"name": ["Trajectum College voor ATH GYM HAVO MAVO VBO LWOO"], "brinnr": "24tj", "rad": 5, "selected": "false", "loc": [52.10834980000001, 5.1158893]}, "77": {"name": ["Produs"], "brinnr": "12nw", "rad": 5, "selected": "false", "loc": [51.9562863, 5.8610698]}, "324": {"name": ["CVO 't Gooi  voor Lyc Havo VMBO Lwoo"], "brinnr": "03fo", "rad": 5, "selected": "false", "loc": [52.2345717, 5.146986399999999]}, "322": {"name": ["Murmellius Gymnasium"], "brinnr": "20aa", "rad": 5, "selected": "false", "loc": [52.63416609999999, 4.7391827]}, "297": {"name": ["Mgr Frencken College voor Atheneum en Havo"], "brinnr": "02gf", "rad": 5, "selected": "false", "loc": [51.6366606, 4.858737500000001]}, "185": {"name": ["Gymnasium van de Trevianum Scholengroep"], "brinnr": "04ds", "rad": 5, "selected": "false", "loc": [51.0080809, 5.8496986]}, "646": {"name": ["Vrijzinnig Christelijk Lyceum Scholengemeenschap voor Vwo en Havo"], "brinnr": "02ut", "rad": 5, "selected": "false", "loc": [52.10009950000001, 4.2839012]}, "122": {"name": ["Agnieten College Wezep voor Lyceum Havo Mavo Vbo Lwoo"], "brinnr": "02vt", "rad": 5, "selected": "false", "loc": [52.4677466, 5.9990445]}, "234": {"name": ["Lyceum Bisschop Bekkers voor Gymnnasium, Atheneum en Havo"], "brinnr": "27zf", "rad": 5, "selected": "false", "loc": [51.4772437, 5.4439928]}, "277": {"name": ["Sint Odulphuslyceum Scholengemeenschap voor VWO en HAVO"], "brinnr": "21fv", "rad": 5, "selected": "false", "loc": [51.55760979999999, 5.0775956]}, "494": {"name": ["Het Baarnsch Lyceum"], "brinnr": "02tg", "rad": 5, "selected": "false", "loc": [52.2051143, 5.2903893]}, "569": {"name": ["Gymnasium Novum voor Gymnasium Atheneum Havo Mavo"], "brinnr": "02vo", "rad": 5, "selected": "false", "loc": [52.0740191, 4.3547115]}, "637": {"name": ["Visser t Hooft Lyceum Lyceum Havo Mavo Vbo Lwoo"], "brinnr": "02vd", "rad": 5, "selected": "false", "loc": [52.17234140000001, 4.4825611]}, "364": {"name": ["Scholengroep Zaandam"], "brinnr": "20cn", "rad": 5, "selected": "false", "loc": [52.4501846, 4.813236300000001]}, "523": {"name": ["PENTA college Christelijke Scholengemeenschap voor gym ath havo mavo vmbo lwoo"], "brinnr": "20fr", "rad": 5, "selected": "false", "loc": [51.8499622, 4.3079681]}, "537": {"name": ["Scheepvaart en Transport College"], "brinnr": "05ea", "rad": 5, "selected": "false", "loc": [51.9026778, 4.4604753]}, "211": {"name": ["Katholieke School voor Praktijkonderwijs"], "brinnr": "13fb", "rad": 5, "selected": "false", "loc": [50.8973312, 5.971383899999999]}, "631": {"name": ["Het Rijnlands Sassenheim Scholengemeenschap voor Atheneum Havo Mavo"], "brinnr": "14td", "rad": 5, "selected": "false", "loc": [52.2184791, 4.5172662]}, "526": {"name": ["St Stanislascoll RK SGM v Lyc Havo Mavo Vbo Lwoo"], "brinnr": "02dz", "rad": 5, "selected": "false", "loc": [52.0099069, 4.3465932]}, "449": {"name": ["Thorbecke Scholengemeenschap voor Ath Havo Mavo Vbo Lwoo"], "brinnr": "20db", "rad": 5, "selected": "false", "loc": [52.5140444, 6.123403499999999]}, "354": {"name": ["Haemstede Barger MAVO"], "brinnr": "17hh", "rad": 5, "selected": "false", "loc": [52.3570621, 4.618328]}, "79": {"name": ["Stedelijk Gymnasium Arnhem"], "brinnr": "20rm", "rad": 5, "selected": "false", "loc": [51.98139459999999, 5.9276027]}, "493": {"name": ["Ichthus College Scholengemeenschap voor Atheneum Havo Mavo"], "brinnr": "06su", "rad": 5, "selected": "false", "loc": [52.0258909, 5.5267251]}, "217": {"name": ["Openbare School voor Praktijkonderwijs"], "brinnr": "26kz", "rad": 5, "selected": "false", "loc": [50.8973312, 5.971383899999999]}, "245": {"name": ["Commanderij College voor gymnasium atheneum havo vmbo  en praktijkonderwijs"], "brinnr": "25mg", "rad": 5, "selected": "false", "loc": [51.5589586, 5.689942299999999]}, "105": {"name": ["Scholengemeenschap voor Voortgezet Vrije Schoolonderwijs"], "brinnr": "00cb", "rad": 5, "selected": "false", "loc": [51.8409629, 5.8634382]}, "426": {"name": ["Twents Carmel College voor Gymnasium, Atheneum, Havo, Vmbo met Lwoo, Pro"], "brinnr": "05av", "rad": 5, "selected": "false", "loc": [52.31455889999999, 6.9378158]}, "614": {"name": ["Stedelijk Gymnasium"], "brinnr": "20dp", "rad": 5, "selected": "false", "loc": [52.1531714, 4.5058657]}, "132": {"name": ["Openbare Scholengemeenschap Apeldoorn"], "brinnr": "20kq", "rad": 5, "selected": "false", "loc": [52.22023009999999, 5.9617356]}, "164": {"name": ["School voor Praktijkonderwijs PrO Stadskanaal"], "brinnr": "18uz", "rad": 5, "selected": "false", "loc": [52.98934860000001, 6.9593451]}, "220": {"name": ["KSE (Katholieke Scholengemeenschap Etten-Leur e.o.)"], "brinnr": "00kv", "rad": 5, "selected": "false", "loc": [51.5675892, 4.647698999999999]}, "238": {"name": ["Dongemond College voor Atheneum Havo en Vmbo"], "brinnr": "01iw", "rad": 5, "selected": "false", "loc": [51.7053232, 4.8712575]}, "20": {"name": ["Regionale Scholengemeenschap 't Slingerbos voor Ath Havo Mavo"], "brinnr": "17ck", "rad": 5, "selected": "false", "loc": [52.3283642, 5.5365601]}, "256": {"name": ["Varendonck College voor Atheneum Gymnasium Havo Vmbo Lwoo Pro"], "brinnr": "13pe", "rad": 5, "selected": "false", "loc": [51.3999101, 5.7343095]}, "594": {"name": ["IJsselcollege(VWO,HAVO,MAVO,VMBO,PRO)"], "brinnr": "20bh", "rad": 5, "selected": "false", "loc": [51.9310662, 4.5958745]}, "348": {"name": ["Kennemer College"], "brinnr": "27md", "rad": 5, "selected": "false", "loc": [52.4945622, 4.6632435]}, "48": {"name": ["Nordwin College"], "brinnr": "12vi", "rad": 5, "selected": "false", "loc": [53.2542409, 6.1512672]}, "158": {"name": ["Hogeland College voor Ath Havo Mavo Vbo Lwoo"], "brinnr": "16zk", "rad": 5, "selected": "false", "loc": [53.3915304, 6.5566895]}, "226": {"name": ["Vakcollege Tilburg, sectoren Economie en Groen"], "brinnr": "20gd", "rad": 5, "selected": "false", "loc": [51.576668, 5.0996556]}, "94": {"name": ["School voor Praktijk Onderwijs De Opstap"], "brinnr": "26hv", "rad": 5, "selected": "false", "loc": [52.0190345, 5.666605199999999]}, "529": {"name": ["Christelijke Scholengemeenschap Zandvliet voor Lyceum en Havo"], "brinnr": "14ta", "rad": 5, "selected": "false", "loc": [52.0912951, 4.3431304]}, "375": {"name": ["Solyvius College SGM voor Lyc Havo Mavo Vbo Lwoo"], "brinnr": "19ti", "rad": 5, "selected": "false", "loc": [52.306349, 4.6458577]}, "435": {"name": ["Landstede"], "brinnr": "01aa", "rad": 5, "selected": "false", "loc": [52.51125099999999, 6.1018627]}, "606": {"name": ["Willem De Zwijger College voor Gym, Ath, Havo, en Vmbo"], "brinnr": "20ae", "rad": 5, "selected": "false", "loc": [51.8327369, 4.6838238]}, "475": {"name": ["Vallei College voor Ath Havo Mavo Vbo Lwoo"], "brinnr": "20ei", "rad": 5, "selected": "false", "loc": [52.16913049999999, 5.3869405]}, "218": {"name": ["Gymnasium Bernrode"], "brinnr": "02dw", "rad": 5, "selected": "false", "loc": [51.6541428, 5.4726686]}, "397": {"name": ["Praktijkschool Westfriesland locatie Hoorn"], "brinnr": "07fo", "rad": 5, "selected": "false", "loc": [52.64925119999999, 5.0805489]}, "192": {"name": ["Sophianum Scholengemeenschap in het Heuvelland"], "brinnr": "01gl", "rad": 5, "selected": "false", "loc": [50.7973563, 5.886533]}, "148": {"name": ["MaxX"], "brinnr": "26kr", "rad": 5, "selected": "false", "loc": [52.1295879, 6.6241148]}, "41": {"name": ["Het Baken"], "brinnr": "01fp", "rad": 5, "selected": "false", "loc": [52.3774783, 5.220536]}, "504": {"name": ["Rooms Katholieke Scholengemeenschap Reynaert College Lyceum Havo Mavo Vbo Lwoo"], "brinnr": "25fx", "rad": 5, "selected": "false", "loc": [51.2946217, 4.0747552]}, "95": {"name": ["Scholengemeenschap Mari\ufffdndael VBO LWOO"], "brinnr": "00tq", "rad": 5, "selected": "false", "loc": [51.9831751, 5.9630749]}, "193": {"name": ["Grotiuscollege Stedelijke Scholengemeenschap voor Lyceum Havo Mavo"], "brinnr": "02df", "rad": 5, "selected": "false", "loc": [50.8805691, 5.985134500000001]}, "623": {"name": ["Christelijke Scholengemeenschap voor Atheneum Havo Mavo Willem De Zwijger"], "brinnr": "05ta", "rad": 5, "selected": "false", "loc": [51.9503517, 4.839125399999999]}, "644": {"name": ["Sint Laurenscollege Atheneum en Havo"], "brinnr": "02ug", "rad": 5, "selected": "false", "loc": [51.9651197, 4.4966436]}, "409": {"name": ["Rooms Katholieke Scholengemeenschap Tabor voor Lyceum Havo Mavo Vbo Lwoo"], "brinnr": "02me", "rad": 5, "selected": "false", "loc": [52.6459264, 5.0444905]}, "219": {"name": ["Stedelijk Gymnasium"], "brinnr": "20aj", "rad": 5, "selected": "false", "loc": [51.6900078, 5.289102799999999]}, "463": {"name": ["Globe College, brede school voor vmbo, basis, kader en theoretische leerweg"], "brinnr": "18an", "rad": 5, "selected": "false", "loc": [52.0793973, 5.0992058]}, "264": {"name": ["Instelling Voortgezet Onderwijs Deurne voor ATH HAVO MAVO VBO LWOO"], "brinnr": "17vp", "rad": 5, "selected": "false", "loc": [51.4454673, 5.786062299999999]}, "235": {"name": ["De Nassa, Scholengemeenschap voor Gymn Ath Havo Mavo"], "brinnr": "16qh", "rad": 5, "selected": "false", "loc": [51.5810194, 4.7932302]}, "17": {"name": ["Christelijk Scholengemeenschap Vincent van Gogh Lyceum Havo Mavo Vbo Lwoo"], "brinnr": "02eb", "rad": 5, "selected": "false", "loc": [52.99898719999999, 6.546957600000001]}, "183": {"name": ["DaCapo College Born"], "brinnr": "18de", "rad": 5, "selected": "false", "loc": [51.0328717, 5.8035704]}, "545": {"name": ["Christelijke Scholengemeenschap De Goudse Waarden Lyc Havo Mavo Vbo Lwoo Pro"], "brinnr": "14sf", "rad": 5, "selected": "false", "loc": [52.0145456, 4.697489099999999]}, "180": {"name": ["DaCapocollege Rijksweg Zuid voor Mavo Vbo Lwoo"], "brinnr": "02ib", "rad": 5, "selected": "false", "loc": [50.9900067, 5.852978299999999]}, "130": {"name": ["Van Lodensteincollege Scholengemeenschap voor Lyceum Havo Mavo Vbo Lwoo"], "brinnr": "03wo", "rad": 5, "selected": "false", "loc": [52.168771, 5.4502833]}, "26": {"name": ["Agrarisch Opleidingen Centrum Groenhorst"], "brinnr": "25gv", "rad": 5, "selected": "false", "loc": [52.7098837, 5.743252099999999]}, "591": {"name": ["Coornhert Gymnasium"], "brinnr": "20ai", "rad": 5, "selected": "false", "loc": [52.0214796, 4.7195658]}, "160": {"name": ["Maartenscollege voor Lyceum Havo Mavo"], "brinnr": "01uh", "rad": 5, "selected": "false", "loc": [53.18491400000001, 6.595251699999999]}, "202": {"name": ["Bouwens van der Boije College voor Lyceum Havo Mavo Lwoo Vbo"], "brinnr": "20ll", "rad": 5, "selected": "false", "loc": [51.3201917, 5.9786528]}, "186": {"name": ["HAVO van de Trevianum Scholengroep"], "brinnr": "07bq", "rad": 5, "selected": "false", "loc": [51.0080809, 5.8496986]}, "639": {"name": ["Heerenlanden College"], "brinnr": "17xu", "rad": 5, "selected": "false", "loc": [51.8969391, 5.0926785]}, "201": {"name": ["Scholengemeenschap Groenewald voor Vmbo Havo VWO"], "brinnr": "20ka", "rad": 5, "selected": "false", "loc": [50.9609879, 5.7777949]}, "578": {"name": ["Johan de Witt Scholengroep voor Vwo Havo Mavo Vmbo Pro Lwoo nieuwkomers"], "brinnr": "20mj", "rad": 5, "selected": "false", "loc": [52.0719258, 4.2953946]}, "413": {"name": ["Kolom Praktijkcollege Het Plein"], "brinnr": "10jy", "rad": 5, "selected": "false", "loc": [52.3790558, 4.8167197]}, "458": {"name": ["Scholengemeenschap St Bonifatius College Lyceum Havo"], "brinnr": "02ue", "rad": 5, "selected": "false", "loc": [52.0817521, 5.1376051]}, "75": {"name": ["Olympuscollege PC RK SGM voor Lyceum Havo Mavo"], "brinnr": "05ff", "rad": 5, "selected": "false", "loc": [51.962402, 5.902656200000001]}, "19": {"name": ["Almere College Ontmoetingsschool voor PRO LWOO VMBO HAVO VWO"], "brinnr": "01xn", "rad": 5, "selected": "false", "loc": [52.52516989999999, 5.7075936]}, "289": {"name": ["Beatrix College voor Mavo, Havo, Atheneum"], "brinnr": "18xu", "rad": 5, "selected": "false", "loc": [51.5767534, 4.9956659]}, "575": {"name": ["Scholengemeenschap het Segbroekcollege Vwo Havo Mavo"], "brinnr": "20ma", "rad": 5, "selected": "false", "loc": [52.0727147, 4.257034600000001]}, "315": {"name": ["osg Willem Blaeu voor vwo havo mavo en vbo"], "brinnr": "01xf", "rad": 5, "selected": "false", "loc": [52.6396998, 4.7222136]}, "510": {"name": ["PC/RK School voor Praktijkonderwijs De Sprong"], "brinnr": "26ll", "rad": 5, "selected": "false", "loc": [51.3229123, 3.851820099999999]}, "387": {"name": ["Regius College Emmalaan Praktijkonderwijs"], "brinnr": "19sq", "rad": 5, "selected": "false", "loc": [52.7840515, 4.795596199999999]}, "81": {"name": ["Openb. SGM. Arnhem Noord. voor lyceum, havo, mavo en vbo"], "brinnr": "25gl", "rad": 5, "selected": "false", "loc": [51.9955284, 5.9404445]}, "296": {"name": ["Orion Lyceum voor vwo en havo"], "brinnr": "28db", "rad": 5, "selected": "false", "loc": [51.6066847, 4.7804631]}, "66": {"name": ["Openbare Scholengroep  voor VMBO, Havo, Atheneum en Gymnasium"], "brinnr": "14fw", "rad": 5, "selected": "false", "loc": [52.9700721, 5.9120941]}, "488": {"name": ["Anna Van Ryn College Opbare Scholengemeenschap voor Ath Havo Mavo Vbo"], "brinnr": "18ws", "rad": 5, "selected": "false", "loc": [52.02033770000001, 5.0764836]}, "265": {"name": ["Rythovius College Scholengemeenschap voor Lyc Havo Mavo"], "brinnr": "18xr", "rad": 5, "selected": "false", "loc": [51.36278300000001, 5.312010799999999]}, "115": {"name": ["Stedelijke Scholengemeenschap Nijmegen"], "brinnr": "20eo", "rad": 5, "selected": "false", "loc": [51.82429519999999, 5.8452316]}, "341": {"name": ["Fons Vitae Lyceum Rooms Katholiek Scholengemeenschap voor Vwo en Havo"], "brinnr": "02an", "rad": 5, "selected": "false", "loc": [52.3514899, 4.8791528]}, "393": {"name": ["Scholengemeenschap ZAAM West voor Vwo Havo Mavo Vbo Lwoo"], "brinnr": "17hb", "rad": 5, "selected": "false", "loc": [52.361472, 4.840538]}, "335": {"name": ["St Vituscollege Bussum/Naarden"], "brinnr": "02ub", "rad": 5, "selected": "false", "loc": [52.2704318, 5.1551342]}, "338": {"name": ["Gooise Scholenfederatie vwo, havo, vmbo"], "brinnr": "14sm", "rad": 5, "selected": "false", "loc": [52.2792709, 5.165917100000001]}, "255": {"name": ["Rodenborchcollege Rooms Katholieke Scholengemeenschap voor Atheneum Havo Mavo"], "brinnr": "07mu", "rad": 5, "selected": "false", "loc": [51.7173977, 5.3785053]}, "361": {"name": ["Chr Sgm Buitenveldert v Gymn Ath Havo en Mavo"], "brinnr": "14vy", "rad": 5, "selected": "false", "loc": [52.3236036, 4.8635166]}, "383": {"name": ["Voorgezet Onderwijs van Amsterdam voor Lyceum Havo Mavo Vbo Lwoo"], "brinnr": "21as", "rad": 5, "selected": "false", "loc": [52.385599, 4.9107639]}, "329": {"name": ["Esprit Scholen voor Lyceum Havo Mavo Vbo Lwoo"], "brinnr": "17ys", "rad": 5, "selected": "false", "loc": [52.3728244, 4.829926599999999]}, "92": {"name": ["Montessori College voor Vwo, Havo, Vmbo"], "brinnr": "00rz", "rad": 5, "selected": "false", "loc": [51.8290196, 5.8928904]}, "174": {"name": ["Eemsdeltacollege voor vwo, havo mavo en vbo"], "brinnr": "30pp", "rad": 5, "selected": "false", "loc": [53.3224268, 6.884391099999999]}, "546": {"name": ["Praktijkschool De Goudse Waarden"], "brinnr": "30ff", "rad": 5, "selected": "false", "loc": [52.0145456, 4.697489099999999]}, "499": {"name": ["Christelijk Lyceum Scholengemeenschap voor Mavo Havo Lyceum"], "brinnr": "02vm", "rad": 5, "selected": "false", "loc": [52.0130709, 5.545005199999999]}, "44": {"name": ["Openbare school voor vmbo De Krijtenburg"], "brinnr": "19eo", "rad": 5, "selected": "false", "loc": [53.298478, 5.073859]}, "9": {"name": ["Praktijkschool Emmen"], "brinnr": "26hx", "rad": 5, "selected": "false", "loc": [52.7757405, 6.946748899999999]}, "429": {"name": ["PC/RK Scholengemeenschap De Grundel voor Lyceum Havo Mavo Vbo Lwoo"], "brinnr": "18cr", "rad": 5, "selected": "false", "loc": [52.2627015, 6.808037199999999]}, "99": {"name": ["Regionale Scholengemeenschap Het Rhedens voor Lyceum Havo Mavo Vbo"], "brinnr": "02vn", "rad": 5, "selected": "false", "loc": [52.0043339, 5.971376299999999]}, "38": {"name": ["Praktijkonderwijs Almere-Marathonlaan"], "brinnr": "28bu", "rad": 5, "selected": "false", "loc": [52.4017819, 5.310886399999999]}, "612": {"name": ["Einstein Lyceum Openbare Scholengemeenschap voor Mavo Havo Ath Gymn"], "brinnr": "17cr", "rad": 5, "selected": "false", "loc": [51.8569207, 4.3599483]}, "500": {"name": ["Scheldemond College"], "brinnr": "16yc", "rad": 5, "selected": "false", "loc": [51.4630924, 3.5811774]}, "563": {"name": ["LMC Praktijkonderwijs Schietbaanstraat"], "brinnr": "29vz", "rad": 5, "selected": "false", "loc": [51.9158084, 4.4646533]}, "304": {"name": ["Mavoschool Sancta Maria"], "brinnr": "01gv", "rad": 5, "selected": "false", "loc": [51.6991875, 5.312058899999999]}, "619": {"name": ["Grotius College voor Lyceum Havo Mavo Vbo Lwoo"], "brinnr": "20ab", "rad": 5, "selected": "false", "loc": [51.9987876, 4.3468212]}, "410": {"name": ["Jan Arentsz Christelijke Scholengemeenschap voor Lyceum Havo Mavo Vbo"], "brinnr": "02td", "rad": 5, "selected": "false", "loc": [52.6484094, 4.750592699999999]}, "534": {"name": ["Christelijk Scholengemeenschap voor Lyceum Havo Mavo Vbo Lwoo Insula College"], "brinnr": "02ci", "rad": 5, "selected": "false", "loc": [51.8051262, 4.6920147]}, "483": {"name": ["Leidsche Rijn College voor GYM ATH HAVO MAVO VBO LWOO"], "brinnr": "24tr", "rad": 5, "selected": "false", "loc": [52.0923868, 5.061916999999999]}, "347": {"name": ["Jac P Thijsse College voor Vwo Havo Mavo"], "brinnr": "20mh", "rad": 5, "selected": "false", "loc": [52.55318310000001, 4.6834577]}, "415": {"name": ["Kolom Praktijkcollege De Dreef"], "brinnr": "27vh", "rad": 5, "selected": "false", "loc": [52.32323299999999, 4.941761]}, "39": {"name": ["Praktijkonderwijs-Almere Koningsbeltweg"], "brinnr": "30ud", "rad": 5, "selected": "false", "loc": [52.371891, 5.2745902]}, "416": {"name": ["Rooms Katholieke Scholengemeenschap St Michaelcollege voor Atheneum en Havo"], "brinnr": "02tz", "rad": 5, "selected": "false", "loc": [52.4738665, 4.8279287]}, "80": {"name": ["Lorentz Groep"], "brinnr": "20tz", "rad": 5, "selected": "false", "loc": [51.95226719999999, 5.8973302]}, "589": {"name": ["Joh De Wittgymnasium"], "brinnr": "20kz", "rad": 5, "selected": "false", "loc": [51.8086186, 4.6754544]}, "584": {"name": ["Stichting Scholengroep Den Haag Zuid-West"], "brinnr": "20mm", "rad": 5, "selected": "false", "loc": [52.0348806, 4.264327199999999]}, "241": {"name": ["Het Kwadrant School voor Praktijk Onderwijs"], "brinnr": "15is", "rad": 5, "selected": "false", "loc": [51.4837682, 4.3116885]}, "436": {"name": ["Openbare Scholengemeenschap Erasmus Lyceum Havo Mavo Vbo Lwoo"], "brinnr": "04hr", "rad": 5, "selected": "false", "loc": [52.361617, 6.6586423]}, "384": {"name": ["Voortgezet Onderwijs van Amsterdam voor Vbo en Lwoo"], "brinnr": "00ef", "rad": 5, "selected": "false", "loc": [52.3394553, 4.8962653]}, "543": {"name": ["Erasmuscollege voor Vwo Havo en Mavo"], "brinnr": "00pj", "rad": 5, "selected": "false", "loc": [52.0612946, 4.5028594]}, "50": {"name": ["Dockingacollege Chr SGS VMBO/HAVO/VWO"], "brinnr": "00zx", "rad": 5, "selected": "false", "loc": [53.3165559, 6.0002121]}, "184": {"name": ["Atheneum van de Trevianum Scholengroep"], "brinnr": "01mo", "rad": 5, "selected": "false", "loc": [51.0080809, 5.8496986]}, "96": {"name": ["Isendoorn College voor Mavo Havo en Atheneum"], "brinnr": "08lp", "rad": 5, "selected": "false", "loc": [52.1341876, 6.2214828]}, "495": {"name": ["Werkplaats Kindergemeenschap"], "brinnr": "17wp", "rad": 5, "selected": "false", "loc": [52.1347089, 5.1964521]}, "379": {"name": ["Linnaeus College Haarlem voor Lyceum Havo Mavo Vbo Lwoo"], "brinnr": "25fu", "rad": 5, "selected": "false", "loc": [52.403597, 4.636356399999999]}, "1": {"name": ["Openbare Scholengemeenschap Dr Nassau College voor Vwo Havo Mavo Vbo Lwoo"], "brinnr": "20lo", "rad": 5, "selected": "false", "loc": [53.0037859, 6.561177]}, "355": {"name": ["Kaj Munk College voor Atheneum Havo Mavo"], "brinnr": "21we", "rad": 5, "selected": "false", "loc": [52.3095177, 4.6798804]}, "293": {"name": ["Rooms Katholiek Gymnasium Juvenaat Heilig Hart"], "brinnr": "16qn", "rad": 5, "selected": "false", "loc": [51.4869139, 4.2930971]}, "420": {"name": ["De Waerdenborch Scholengemeenschap voor Atheneum Havo Mavo Vbo"], "brinnr": "19ff", "rad": 5, "selected": "false", "loc": [52.280734, 6.4185618]}, "117": {"name": ["Citadel College voor vwo havo mavo vbo en lwoo"], "brinnr": "30au", "rad": 5, "selected": "false", "loc": [51.8695516, 5.8568889]}, "248": {"name": ["Ds. Pierson College voor Mavo Havo Atheneum"], "brinnr": "05pl", "rad": 5, "selected": "false", "loc": [51.6994483, 5.3174078]}, "59": {"name": ["Scholengemeenschap Ulbe Van Houten Christelijke SGM voor Vmbo"], "brinnr": "01be", "rad": 5, "selected": "false", "loc": [53.2790613, 5.66106]}, "178": {"name": ["College Den Hulster Scholengemeenschap voor ATH HAVO MAVO VBO LWOO"], "brinnr": "16xd", "rad": 5, "selected": "false", "loc": [51.3555196, 6.1638926]}, "337": {"name": ["Gooise Praktijkschool"], "brinnr": "11ai", "rad": 5, "selected": "false", "loc": [52.1951262, 5.168736]}, "365": {"name": ["Scholengroep Krommenie"], "brinnr": "20ey", "rad": 5, "selected": "false", "loc": [52.4971589, 4.757911500000001]}, "400": {"name": ["Scholengemeenschap Panta Rhei voor vmbo/mavo en Lwoo"], "brinnr": "00wd", "rad": 5, "selected": "false", "loc": [52.3027211, 4.878974899999999]}, "13": {"name": ["Gereformeerde Scholengemeenschap voor Lyceum Havo Mavo Vbo Lwoo"], "brinnr": "02uv", "rad": 5, "selected": "false", "loc": [53.0014854, 6.562991999999999]}, "288": {"name": ["Koning Willem Ii College voor Lyc Havo Mavo"], "brinnr": "16mq", "rad": 5, "selected": "false", "loc": [51.5419023, 5.083543199999999]}, "143": {"name": ["Almende College voor Gymnasium Atheneum Havo Mavo Vbo Lwoo"], "brinnr": "14um", "rad": 5, "selected": "false", "loc": [51.9129952, 6.3756939]}, "610": {"name": ["Wolfert van Borselen scholengroep"], "brinnr": "15kr", "rad": 5, "selected": "false", "loc": [51.925711, 4.4570629]}, "276": {"name": ["Theresialyceum voor gymnasium atheneum en havo"], "brinnr": "21ex", "rad": 5, "selected": "false", "loc": [51.56126459999999, 5.0549994]}, "18": {"name": ["Christelijke Scholengemeenschap Dingstede voor Mavo Havo en Atheneum"], "brinnr": "03xm", "rad": 5, "selected": "false", "loc": [52.6897321, 6.1824454]}, "30": {"name": ["Openbare School voor voortgezet onderwijs Zuyderzee College"], "brinnr": "20cr", "rad": 5, "selected": "false", "loc": [52.7148491, 5.7584577]}, "73": {"name": ["Inspecteur Boelensschool voor Mavo"], "brinnr": "02xq", "rad": 5, "selected": "false", "loc": [53.4794724, 6.163253999999999]}, "620": {"name": ["Krimpenerwaard College voor Lyceum Havo Mavo"], "brinnr": "14wl", "rad": 5, "selected": "false", "loc": [51.9206862, 4.5207972]}, "214": {"name": ["Ath vh Bernardinuscol"], "brinnr": "19hv", "rad": 5, "selected": "false", "loc": [50.8805691, 5.985134500000001]}, "513": {"name": ["Stedelijke Scholengemeenschap De Rede voor Lyc Havo Mavo Vbo Lwoo"], "brinnr": "16jo", "rad": 5, "selected": "false", "loc": [51.3199519, 3.839651]}, "385": {"name": ["Voorgezet Onderwijs van Amsterdam voor Vbo, Lwoo en Praktijkonderwijs"], "brinnr": "14rl", "rad": 5, "selected": "false", "loc": [52.3473479, 4.9142442]}, "318": {"name": ["rsg Wiringherlant voor vwo havo mavo en vbo"], "brinnr": "17dd", "rad": 5, "selected": "false", "loc": [52.8478986, 5.024089399999999]}, "253": {"name": ["Baanderherencollege Vmbo"], "brinnr": "04xu", "rad": 5, "selected": "false", "loc": [51.5963934, 5.315950099999999]}, "333": {"name": ["Verenigde Scholen J.A. Alberdingk Thijm Voortgezet Onderwijs"], "brinnr": "00ps", "rad": 5, "selected": "false", "loc": [52.2202485, 5.180696999999999]}, "376": {"name": ["Openbare Scholengemeenschap Vellesan College Ath Havo Mavo Vbo Lwoo"], "brinnr": "20ek", "rad": 5, "selected": "false", "loc": [52.4603061, 4.6303436]}, "351": {"name": ["Scholengemeenschap Eerste Christelijk Lyceum Vwo en Havo"], "brinnr": "01lz", "rad": 5, "selected": "false", "loc": [52.3719803, 4.6195676]}, "104": {"name": ["Pro College Wijchen voor praktijkonderwijs"], "brinnr": "26ky", "rad": 5, "selected": "false", "loc": [51.8083763, 5.7381877]}, "89": {"name": ["Scholengemeenschap voor Vwo Dorenweerd College"], "brinnr": "02sy", "rad": 5, "selected": "false", "loc": [51.9839564, 5.7970836]}, "366": {"name": ["Saenredam College voor ATH HAVO MAVO VBO LWOO"], "brinnr": "20fc", "rad": 5, "selected": "false", "loc": [52.4751575, 4.7989861]}, "317": {"name": ["Berger Scholengemeenschap voor vwo havo en mavo"], "brinnr": "16st", "rad": 5, "selected": "false", "loc": [52.6709514, 4.691220899999999]}, "561": {"name": ["LMC Praktijkonderwijs Talingstraat"], "brinnr": "29vw", "rad": 5, "selected": "false", "loc": [51.8855517, 4.4666617]}, "176": {"name": ["Praktijkonderwijs Roermond"], "brinnr": "23hh", "rad": 5, "selected": "false", "loc": [51.1726601, 6.0022243]}, "451": {"name": ["Rembrandt College Openbare Scholengemeenschap voor Mavo Havo Ath"], "brinnr": "19ip", "rad": 5, "selected": "false", "loc": [52.0209207, 5.546439100000001]}, "640": {"name": ["Grafisch Lyceum Rotterdam voor Mbo Bbo Mavo Vbo"], "brinnr": "23ja", "rad": 5, "selected": "false", "loc": [51.93161019999999, 4.462040099999999]}, "599": {"name": ["Stedelyk Gymnasium"], "brinnr": "20dc", "rad": 5, "selected": "false", "loc": [51.9275349, 4.3738318]}, "243": {"name": ["W v Oranje Coll Chr SGM v Ath Havo Mavo Vbo Lwoo"], "brinnr": "01gh", "rad": 5, "selected": "false", "loc": [51.6762533, 5.0463174]}, "198": {"name": ["Romboutscollege voor Atheneum Havo en Mavo"], "brinnr": "18do", "rad": 5, "selected": "false", "loc": [50.9385183, 5.9720656]}, "287": {"name": ["Scholengemeenschap De Rooi Pannen"], "brinnr": "25lv", "rad": 5, "selected": "false", "loc": [51.568934, 5.064009599999999]}, "503": {"name": ["Christelijke Scholengemeenschap Walcheren voor Lyceum Havo Mavo Vbo Lwoo"], "brinnr": "03xs", "rad": 5, "selected": "false", "loc": [51.50237869999999, 3.5992718]}, "67": {"name": ["De Compagnie Praktijkonderwijs Sevenwolden"], "brinnr": "26kp", "rad": 5, "selected": "false", "loc": [52.9679341, 5.9209637]}, "246": {"name": ["Strabrechtcollege Scholengemeenschap voor LYC HAVO MAVO"], "brinnr": "01xl", "rad": 5, "selected": "false", "loc": [51.425933, 5.5772745]}, "27": {"name": ["AOC Groenhorst Almere Afdeling VMBO-groen"], "brinnr": "27vd", "rad": 5, "selected": "false", "loc": [52.3474109, 5.1673715]}, "434": {"name": ["Vechtdal College Scholengemeenschap voor Atheneum Havo Mavo Vbo Lwoo"], "brinnr": "02ux", "rad": 5, "selected": "false", "loc": [52.5709305, 6.6244441]}, "326": {"name": ["Montessori Scholengemeenschap Amsterdam voor Lyceum Havo Mavo Vbo Lwoo"], "brinnr": "16ps", "rad": 5, "selected": "false", "loc": [52.35616539999999, 4.885115799999999]}, "146": {"name": ["Het Stedelijk, scholengroep voor openbaar Lyceum Havo Mavo Vbo Lwoo"], "brinnr": "20dh", "rad": 5, "selected": "false", "loc": [52.1438242, 6.2004489]}, "471": {"name": ["Het Nieuwe Lyceum Scholengemeenschap voor Gymnasium Atheneum en Havo"], "brinnr": "00tl", "rad": 5, "selected": "false", "loc": [52.1323365, 5.2008896]}, "251": {"name": ["Maurick College Scholengemeenschap voor vmbo, havo, atheneum en gymnasium"], "brinnr": "02qt", "rad": 5, "selected": "false", "loc": [51.6503162, 5.2813897]}, "109": {"name": ["Kandinsky College voor Lyceum Havo Mavo Vbo Lwoo"], "brinnr": "02st", "rad": 5, "selected": "false", "loc": [51.80380330000001, 5.8318033]}, "57": {"name": ["Christelijke Scholengemeenschap A.M. van Schurman voor Havo Mavo Vbo"], "brinnr": "14ns", "rad": 5, "selected": "false", "loc": [53.1956549, 5.5382718]}, "222": {"name": ["Elde College Schijndel voor VWO HAVO VMBO LWOO en PRO"], "brinnr": "04gu", "rad": 5, "selected": "false", "loc": [51.61555749999999, 5.426247699999999]}, "638": {"name": ["Bonaventuracollege SGM voor Gym. Ath. Havo Vmbo"], "brinnr": "21gw", "rad": 5, "selected": "false", "loc": [52.1512389, 4.5054911]}, "121": {"name": ["Praktijkschool Arentheem"], "brinnr": "26jt", "rad": 5, "selected": "false", "loc": [51.9828005, 5.9456532]}, "311": {"name": ["Gymnasium Felisenum"], "brinnr": "20dg", "rad": 5, "selected": "false", "loc": [52.455222, 4.6386515]}, "381": {"name": ["Zuiderzee College voor VMBO"], "brinnr": "29yt", "rad": 5, "selected": "false", "loc": [52.4533862, 4.8324508]}, "455": {"name": ["Amadeus Lyceum"], "brinnr": "00ro", "rad": 5, "selected": "false", "loc": [52.094127, 5.011379499999999]}, "602": {"name": ["Praktijk College Brielle"], "brinnr": "14ap", "rad": 5, "selected": "false", "loc": [51.8932296, 4.1728686]}, "308": {"name": ["Altena College Christelijke Scholengemeenschap voor Atheneum Havo en Mavo"], "brinnr": "02xs", "rad": 5, "selected": "false", "loc": [51.8090526, 4.9479564]}, "6": {"name": ["rsg de Borgen voor Lyceum Havo mavo Vbo Lwoo"], "brinnr": "00di", "rad": 5, "selected": "false", "loc": [53.1411145, 6.4118928]}, "88": {"name": ["Christelijk College Nassau-Veluwe"], "brinnr": "02fb", "rad": 5, "selected": "false", "loc": [52.33937479999999, 5.6210283]}, "596": {"name": ["ProNovaCollege voor Praktijkonderwijs"], "brinnr": "18vx", "rad": 5, "selected": "false", "loc": [51.9172944, 4.3869889]}, "608": {"name": ["Openbare Scholengemeenschap Libanon Lyceum voor VWO HAVO MAVO"], "brinnr": "15eo", "rad": 5, "selected": "false", "loc": [51.9312633, 4.504323299999999]}, "520": {"name": ["Melanchthon christelijke scholengemeenschap voor gymnasium atheneum havo vmbo"], "brinnr": "18ch", "rad": 5, "selected": "false", "loc": [51.9517894, 4.474014299999999]}, "207": {"name": ["Sint-Maartenscollege"], "brinnr": "27zh", "rad": 5, "selected": "false", "loc": [50.8469924, 5.7463562]}, "72": {"name": ["School voor Christelijk Mavo De Saad"], "brinnr": "02xe", "rad": 5, "selected": "false", "loc": [53.2885499, 5.996989999999999]}, "468": {"name": ["Kalsbeek College Christelijke Scholengemeenschap voor Vmbo, Havo, Ath. en Gymn."], "brinnr": "04ix", "rad": 5, "selected": "false", "loc": [52.0895676, 4.8711046]}, "515": {"name": ["Isaac Beeckman Academie Kapelle"], "brinnr": "29zt", "rad": 5, "selected": "false", "loc": [51.4807751, 3.9567166]}, "45": {"name": ["Openbare Scholengemeenschap Singelland voor Lyceum Havo Mavo Vbo Lwoo"], "brinnr": "04ye", "rad": 5, "selected": "false", "loc": [53.1122153, 6.0999668]}, "448": {"name": ["Gymnasium Celeanum"], "brinnr": "20cf", "rad": 5, "selected": "false", "loc": [52.5313296, 6.094808899999999]}, "149": {"name": ["Nuborgh College"], "brinnr": "01fu", "rad": 5, "selected": "false", "loc": [52.4460486, 5.8662572]}, "509": {"name": ["Algemeen Bijzonder School voor Praktijkonderwijs De Wissel"], "brinnr": "26hf", "rad": 5, "selected": "false", "loc": [51.5010863, 3.9012418]}, "528": {"name": ["Hofstede-PrO School voor Praktijkonderwijs"], "brinnr": "04nf", "rad": 5, "selected": "false", "loc": [52.038881, 4.269218]}, "490": {"name": ["Mgr A E Rientjes Mavo"], "brinnr": "17hx", "rad": 5, "selected": "false", "loc": [52.13834259999999, 5.012708099999999]}, "223": {"name": ["MET Praktijkonderwijs Waalwijk"], "brinnr": "23db", "rad": 5, "selected": "false", "loc": [51.6737577, 5.0464098]}, "598": {"name": ["Het College Vos"], "brinnr": "20cj", "rad": 5, "selected": "false", "loc": [51.9275679, 4.3519664]}, "562": {"name": ["LMC Praktijkonderwijs Huismanstraat"], "brinnr": "29vx", "rad": 5, "selected": "false", "loc": [51.8851363, 4.463133300000001]}, "266": {"name": ["Merlet College Lyc Havo Mavo Vbo Lwoo"], "brinnr": "19rx", "rad": 5, "selected": "false", "loc": [51.72577219999999, 5.8839856]}, "11": {"name": ["Regionale Scholengemeenschap Stad en Esch voor Lyceum Havo Mavo Vbo Lwoo"], "brinnr": "25cl", "rad": 5, "selected": "false", "loc": [52.6916629, 6.1986968]}, "127": {"name": ["Praktijkschool Apeldoorn"], "brinnr": "26kv", "rad": 5, "selected": "false", "loc": [52.1931416, 5.966973299999999]}, "511": {"name": ["Pontes voor Lyceum Atheneum Havo Mavo Vbo Pro en Lwoo"], "brinnr": "13or", "rad": 5, "selected": "false", "loc": [51.5040688, 3.9068865]}, "157": {"name": ["Openbare Scholengemeenschap Winkler Prins voor ATH HAVO MAVO VBO LWOO"], "brinnr": "16pi", "rad": 5, "selected": "false", "loc": [53.1106871, 6.8670078]}, "137": {"name": ["Rsgm Noord Oost Veluwe Ath Havo Mavo Vbo Lwoo"], "brinnr": "13jo", "rad": 5, "selected": "false", "loc": [52.35437839999999, 5.9625813]}, "486": {"name": ["Openbare Scholengroep Schoonoord"], "brinnr": "17bi", "rad": 5, "selected": "false", "loc": [52.0753453, 5.2378083]}, "323": {"name": ["Gemeentelijk Gymnasium"], "brinnr": "20dd", "rad": 5, "selected": "false", "loc": [52.222977, 5.1599244]}, "285": {"name": ["Regionale Scholengemeenschap 't Rijks School voor Lyceum Havo Mavo"], "brinnr": "10lu", "rad": 5, "selected": "false", "loc": [51.4984906, 4.2821403]}, "440": {"name": ["RSG Tromp Meesters Praktijkschool"], "brinnr": "29vy", "rad": 5, "selected": "false", "loc": [52.7896768, 6.12212]}, "140": {"name": ["PC SGM Ulenhof College v Ath Havo Mavo Vbo Lwoo"], "brinnr": "02fc", "rad": 5, "selected": "false", "loc": [51.968809, 6.309529899999999]}, "70": {"name": ["Christelijke School voor Praktijkonderwijs J J Boumanschool"], "brinnr": "05ne", "rad": 5, "selected": "false", "loc": [53.32085069999999, 5.9863956]}, "237": {"name": ["Het Hooghuis"], "brinnr": "19xh", "rad": 5, "selected": "false", "loc": [51.76630129999999, 5.5261346]}, "518": {"name": ["Marnix Gymnasium"], "brinnr": "14qt", "rad": 5, "selected": "false", "loc": [51.9218456, 4.448392999999999]}, "344": {"name": ["Scholen aan Zee 2"], "brinnr": "00mv", "rad": 5, "selected": "false", "loc": [52.940269, 4.750138]}, "56": {"name": ["Bornego College Chr. Scholengemeenschap voor VMBO, Havo, Atheneum en Gymnasium"], "brinnr": "25cv", "rad": 5, "selected": "false", "loc": [52.950267, 5.9243134]}, "492": {"name": ["Cals College Roomskatholiek Scholengemeenschap voor Lyceum Havo Mavo Vbo"], "brinnr": "00vy", "rad": 5, "selected": "false", "loc": [52.02735510000001, 5.0965361]}, "58": {"name": ["Linde College voor Atheneum Havo Mavo Vbo en Lwoo"], "brinnr": "19lo", "rad": 5, "selected": "false", "loc": [52.8819844, 6.008489099999999]}, "136": {"name": ["Staring College Regionale Scholengemeenschap voor Ath Gymn Havo Vmbo"], "brinnr": "24tf", "rad": 5, "selected": "false", "loc": [52.1501411, 6.3960083]}, "374": {"name": ["Hartenlustsch voor Mavo"], "brinnr": "19eq", "rad": 5, "selected": "false", "loc": [52.40291999999999, 4.6224263]}, "21": {"name": ["De Steiger school voor Praktijkonderwijs"], "brinnr": "18pr", "rad": 5, "selected": "false", "loc": [52.4991081, 5.4897498]}, "120": {"name": ["Arentheem College Interconfessionele School voor Atheneum Gymnasium Havo Vmbo"], "brinnr": "07pk", "rad": 5, "selected": "false", "loc": [51.9936398, 5.9256001]}, "446": {"name": ["T Genseler"], "brinnr": "23ej", "rad": 5, "selected": "false", "loc": [52.2496942, 6.8103981]}, "170": {"name": ["Praedinius Gymnasium"], "brinnr": "20bv", "rad": 5, "selected": "false", "loc": [53.2211354, 6.5709748]}, "194": {"name": ["Het College voor Lyc Havo Mavo Vbo lwoo"], "brinnr": "02zr", "rad": 5, "selected": "false", "loc": [51.2428886, 5.6911875]}, "4": {"name": ["Agrarisch Opleidingscentrum Terra"], "brinnr": "01nj", "rad": 5, "selected": "false", "loc": [52.9901324, 6.5792115]}, "388": {"name": ["Atlas College voor Lyceum Havo Mavo Vbo Lwoo"], "brinnr": "25da", "rad": 5, "selected": "false", "loc": [52.64437359999999, 5.0676017]}, "269": {"name": ["Van Maerlantlyceum"], "brinnr": "20ga", "rad": 5, "selected": "false", "loc": [51.4277478, 5.4735168]}, "33": {"name": ["Scholengemeenschap Lelystad voor Ath Havo Mavo Vbo Lwoo"], "brinnr": "18dq", "rad": 5, "selected": "false", "loc": [52.5241049, 5.4756731]}, "382": {"name": ["Calandlyceum voor Gymnasium Atheneum Havo Vmbo"], "brinnr": "21gd", "rad": 5, "selected": "false", "loc": [52.35419539999999, 4.8106231]}, "272": {"name": ["Sint-Janslyceum School voor Gymnasium Atheneum Havo en Mavo"], "brinnr": "20st", "rad": 5, "selected": "false", "loc": [51.6793029, 5.3177075]}, "106": {"name": ["Pronova"], "brinnr": "26md", "rad": 5, "selected": "false", "loc": [51.9702486, 6.7041675]}, "3": {"name": ["Regionale Scholengemeenschap Wolfsbos"], "brinnr": "19iw", "rad": 5, "selected": "false", "loc": [52.7187654, 6.495513799999999]}, "457": {"name": ["Sint Gregorius College Scholengemeenschap voor Atheneum Havo Mavo"], "brinnr": "01kf", "rad": 5, "selected": "false", "loc": [52.0921605, 5.1265592]}, "76": {"name": ["Symbion School voor Praktijkonderwijs"], "brinnr": "08ps", "rad": 5, "selected": "false", "loc": [51.9307834, 6.125356099999999]}, "331": {"name": ["Erfgooiers College Atheneum Havo VMBO-TL"], "brinnr": "00um", "rad": 5, "selected": "false", "loc": [52.29848089999999, 5.2429796]}, "544": {"name": ["Het Vlietland College Scholengemeenschap voor Vwo Havo Mavo"], "brinnr": "14wj", "rad": 5, "selected": "false", "loc": [52.13917739999999, 4.4729141]}, "601": {"name": ["SG Helinium voor Atheneum Havo Mavo Vbo Lwoo"], "brinnr": "12rb", "rad": 5, "selected": "false", "loc": [51.8354143, 4.1186811]}, "107": {"name": ["Christelijk Voortgezet Onderwijs Apeldoorn"], "brinnr": "08sg", "rad": 5, "selected": "false", "loc": [52.19355179999999, 5.9959501]}, "215": {"name": ["School voor Havo Mavo V H Bernardinuscollege"], "brinnr": "19qc", "rad": 5, "selected": "false", "loc": [50.8805691, 5.985134500000001]}, "421": {"name": ["PrO Hardenberg school voorChristelijk Praktijkonderwijs"], "brinnr": "03kz", "rad": 5, "selected": "false", "loc": [52.5740399, 6.633145900000001]}, "46": {"name": ["Openbare Scholengemeenschap Piter Jelles voor Lyceum Havo Mavo Vbo Lwoo"], "brinnr": "20dl", "rad": 5, "selected": "false", "loc": [53.1861326, 5.8044661]}, "467": {"name": ["Meridiaancollege RK SGM v Lyc Havo Mavo Vbo Lwoo"], "brinnr": "00ml", "rad": 5, "selected": "false", "loc": [52.1455415, 5.3546548]}, "437": {"name": ["PrO Erasmus"], "brinnr": "19up", "rad": 5, "selected": "false", "loc": [52.3706213, 6.6681431]}, "367": {"name": ["Praktijkschool De Brug"], "brinnr": "20ff", "rad": 5, "selected": "false", "loc": [52.4928333, 4.7607117]}, "390": {"name": ["Open Sgm Bylmer Vath Havo Mavo Lhno Lto Leao"], "brinnr": "03aq", "rad": 5, "selected": "false", "loc": [52.3186021, 4.9661721]}, "116": {"name": ["Mondial College"], "brinnr": "21sk", "rad": 5, "selected": "false", "loc": [51.83192709999999, 5.7807518]}, "310": {"name": ["Regionale Scholengemeenschap Enkhuizen voor MAVO HAVO VWO"], "brinnr": "13ee", "rad": 5, "selected": "false", "loc": [52.7084121, 5.270513]}, "389": {"name": ["Amstelveen College Opb Ssm voor Gymnasium Havo en Mavo"], "brinnr": "19xy", "rad": 5, "selected": "false", "loc": [52.2907613, 4.853752]}, "161": {"name": ["PC en RK SGM Ubbo Emmius SGM v Lyc Havo Mavo Vbo"], "brinnr": "02vj", "rad": 5, "selected": "false", "loc": [52.9858493, 6.9494525]}, "90": {"name": ["Het Assink lyceum voor Lyceum Havo Mavo Vbo Lwoo"], "brinnr": "05fb", "rad": 5, "selected": "false", "loc": [52.0951312, 6.669313499999999]}, "135": {"name": ["Johannes Fontanus College Christelijk Scholengemeenschap voor Mavo Havo Atheneum"], "brinnr": "00sz", "rad": 5, "selected": "false", "loc": [52.150195, 5.5824866]}, "113": {"name": ["Pax Christi College - scholengemeenschap voor vwo havo vmbo lwoo"], "brinnr": "17ir", "rad": 5, "selected": "false", "loc": [51.889117, 5.615799399999999]}, "487": {"name": ["Houtens"], "brinnr": "30be", "rad": 5, "selected": "false", "loc": [52.0287661, 5.181902]}, "519": {"name": ["Calvijn Christelijke Scholengemeenschap voor vwo havo mavo vmbo lwoo"], "brinnr": "16pk", "rad": 5, "selected": "false", "loc": [51.882544, 4.508094799999999]}, "204": {"name": ["Dendroncollege RK SGM v Lyc Havo Mavo Vbo Lwoo"], "brinnr": "25gf", "rad": 5, "selected": "false", "loc": [51.4618682, 6.0490206]}, "442": {"name": ["De Boog Christelijke School voor Praktijkonderwijs"], "brinnr": "05vn", "rad": 5, "selected": "false", "loc": [52.5010822, 6.1154357]}, "579": {"name": ["Gemeentelijk Gymnasium Camphusianum"], "brinnr": "19zu", "rad": 5, "selected": "false", "loc": [51.8354034, 4.9608642]}, "642": {"name": ["Griendencollege voor VMBO"], "brinnr": "06wy", "rad": 5, "selected": "false", "loc": [51.8221461, 4.7807527]}, "273": {"name": ["Jeroen Bosch College Scholengemeenschap voor Vwo Havo en Mavo"], "brinnr": "20sy", "rad": 5, "selected": "false", "loc": [51.7056773, 5.3136508]}, "343": {"name": ["Purmerendse Scholengroep voor Gymn Lyc Havo Mavo Vbo Lwoo"], "brinnr": "01eo", "rad": 5, "selected": "false", "loc": [52.5129214, 4.954565]}, "212": {"name": ["Herlecollege Scholengemeenschap voor Vmbo"], "brinnr": "16vm", "rad": 5, "selected": "false", "loc": [50.8992964, 5.978424800000001]}, "291": {"name": ["SiNTLUCAS"], "brinnr": "30bc", "rad": 5, "selected": "false", "loc": [51.4279582, 5.457175100000001]}, "405": {"name": ["Alkwin Kollege Rooms Katholieke Scholengemeenschap voor Vwo en Havo"], "brinnr": "14vg", "rad": 5, "selected": "false", "loc": [52.2456384, 4.8159947]}, "456": {"name": ["Kranenburg, School voor Praktijkonderwijs"], "brinnr": "01ek", "rad": 5, "selected": "false", "loc": [52.0768707, 5.1405395]}, "498": {"name": ["Futura College voor Praktijkonderwijs"], "brinnr": "26ka", "rad": 5, "selected": "false", "loc": [52.0800294, 4.87272]}, "432": {"name": ["Protestants Scholengemeenschap Het Noordik voor Lyceum Havo Mavo Vbo Lwoo"], "brinnr": "02do", "rad": 5, "selected": "false", "loc": [52.3656832, 6.6605561]}, "216": {"name": ["Sintermeertencollege Scholengemeenschap voor Lyceum Havo Mavo"], "brinnr": "19xs", "rad": 5, "selected": "false", "loc": [50.8793494, 5.958560800000001]}, "254": {"name": ["Munnikenheide College voor MAVO VBO LWOO"], "brinnr": "04yx", "rad": 5, "selected": "false", "loc": [51.5706021, 4.6617713]}, "566": {"name": ["Scholengemeenschap Dalton Vatel Voor Lyceum HAVO MAVO VBO LWOO"], "brinnr": "00hi", "rad": 5, "selected": "false", "loc": [52.0749644, 4.3727614]}, "47": {"name": ["RSG Simon Vestdijk voor Ath Havo Mavo Vbo"], "brinnr": "14dc", "rad": 5, "selected": "false", "loc": [53.1693271, 5.426030100000001]}, "568": {"name": ["Sint Maartenscollege Scholengemeenschap voor Vwo Havo en Mavo"], "brinnr": "02mu", "rad": 5, "selected": "false", "loc": [52.0740191, 4.3547115]}, "128": {"name": ["De Brug School voor Praktijkonderwijs"], "brinnr": "26lu", "rad": 5, "selected": "false", "loc": [51.8009225, 5.241461699999999]}, "190": {"name": ["Rooms Katholieke Scholengemeenschap St Ursula voor Vwo Havo Vmbo Lwoo"], "brinnr": "17gt", "rad": 5, "selected": "false", "loc": [51.2088809, 5.927167799999999]}, "525": {"name": ["Accent praktijkonderwijs Hoogvliet"], "brinnr": "28df", "rad": 5, "selected": "false", "loc": [51.8672367, 4.346126]}, "615": {"name": ["Stedelijk Gymnasium Socrates"], "brinnr": "30gd", "rad": 5, "selected": "false", "loc": [52.1696535, 4.498533399999999]}, "362": {"name": ["Vrije School Noord Holland voor Atheneum Havo Mavo"], "brinnr": "16ts", "rad": 5, "selected": "false", "loc": [52.3412225, 4.8628181]}, "112": {"name": ["Dominicus Mavo/Havo/Atheneum/Gymnasium"], "brinnr": "14nq", "rad": 5, "selected": "false", "loc": [51.8431666, 5.8244282]}, "147": {"name": ["PRAKTICON"], "brinnr": "26kh", "rad": 5, "selected": "false", "loc": [51.9584209, 6.3016676]}, "181": {"name": ["DaCapo College Milaanstraat"], "brinnr": "02my", "rad": 5, "selected": "false", "loc": [50.9913712, 5.842835699999999]}, "371": {"name": ["Noordzee Onderwijs Groep voor Praktijkonderwijs"], "brinnr": "13jf", "rad": 5, "selected": "false", "loc": [52.4531789, 4.6023425]}, "427": {"name": ["R.K. Scholengemeenschap  Canisius voor vmbo havo vwo"], "brinnr": "16vi", "rad": 5, "selected": "false", "loc": [52.3758681, 6.6886793]}, "327": {"name": ["Het Amsterdams Lyceum"], "brinnr": "02ap", "rad": 5, "selected": "false", "loc": [52.352233, 4.863883899999999]}, "60": {"name": ["Comenius Christelijke Scholengemeenschap voor Atheneum Havo Vmbo Lwoo Pro"], "brinnr": "02vc", "rad": 5, "selected": "false", "loc": [53.19593949999999, 5.812439599999999]}, "621": {"name": ["Gomarusschool s.g.voor VMBO Havo Atheneum"], "brinnr": "00wh", "rad": 5, "selected": "false", "loc": [51.8478274, 4.9717034]}, "2": {"name": ["School voor Praktijkonderwijs De Meander"], "brinnr": "06dt", "rad": 5, "selected": "false", "loc": [52.7182633, 6.4921043]}, "281": {"name": ["Baanderherencollege Praktijkonderwijs"], "brinnr": "26mz", "rad": 5, "selected": "false", "loc": [51.5963934, 5.315950099999999]}, "61": {"name": ["Christelijk Gymnasium Beyers Naude"], "brinnr": "14wi", "rad": 5, "selected": "false", "loc": [53.1944712, 5.795552499999999]}, "465": {"name": ["Stichting voor Christelijk Voortgezet Onderwijs voor Zuidoost-Utrecht"], "brinnr": "02vr", "rad": 5, "selected": "false", "loc": [52.09349659999999, 5.254527599999999]}, "418": {"name": ["Stichting Joodse Kindergemeenschap Cheider MAVO HAVO VWO"], "brinnr": "23gf", "rad": 5, "selected": "false", "loc": [52.32592520000001, 4.878416]}, "313": {"name": ["Barlaeus Gymnasium"], "brinnr": "21ab", "rad": 5, "selected": "false", "loc": [52.359691, 4.8908298]}, "93": {"name": ["Christelijke Scholengemeenschap Het Streek voor Lyceum Havo Mavo Vbo Lwoo"], "brinnr": "25ge", "rad": 5, "selected": "false", "loc": [52.0194439, 5.6613219]}, "43": {"name": ["Gemeentelijke Scholengemeenschap t Schylger Jouw voor vmbo"], "brinnr": "19et", "rad": 5, "selected": "false", "loc": [53.3845277, 5.2888199]}, "422": {"name": ["Christelijke Scholengemeenschap voor Mavo en Vbo Eekeringe"], "brinnr": "23wu", "rad": 5, "selected": "false", "loc": [52.7858744, 6.1208538]}, "306": {"name": ["Markland College Zevenbergen"], "brinnr": "30eu", "rad": 5, "selected": "false", "loc": [51.64082579999999, 4.6063141]}, "28": {"name": ["Christelijke Scholengemeenschap voor VMBO Harderwijk"], "brinnr": "02ex", "rad": 5, "selected": "false", "loc": [52.32943909999999, 5.5353409]}, "423": {"name": ["Etty Hillesum Lyceum voor Gymnasium Atheneum Havo Vmbo Pro"], "brinnr": "01vj", "rad": 5, "selected": "false", "loc": [52.2706144, 6.160716799999999]}, "604": {"name": ["Openbare Scholengemeenschap De Ring voor Putten voor Ath Havo Mavo"], "brinnr": "19dh", "rad": 5, "selected": "false", "loc": [51.84521119999999, 4.338830700000001]}, "522": {"name": ["Farelcollege Christelijke Scholengemeenschap voor atheneum havo mavo vmbo"], "brinnr": "20am", "rad": 5, "selected": "false", "loc": [51.8773914, 4.5870973]}, "249": {"name": ["Pro College Boxmeer, school voor Praktijkonderwijs"], "brinnr": "30mm", "rad": 5, "selected": "false", "loc": [51.6426291, 5.941595]}, "78": {"name": ["Liemers College SGM voor LYC HAVO MAVO VBO LWOO"], "brinnr": "16sk", "rad": 5, "selected": "false", "loc": [51.9355291, 6.0579673]}, "441": {"name": ["Ichthus College School voor Praktijkonderwijs"], "brinnr": "07zi", "rad": 5, "selected": "false", "loc": [52.5528628, 5.8771882]}, "481": {"name": ["POUWER"], "brinnr": "17ao", "rad": 5, "selected": "false", "loc": [52.1124776, 5.1184065]}, "627": {"name": ["Avicenna College voor vwo, havo, mavo en vbo"], "brinnr": "30wh", "rad": 5, "selected": "false", "loc": [51.8749923, 4.4892642]}, "581": {"name": ["Northgo College Openbare Scholengemeenschap voor Vmbo Havo Vwo"], "brinnr": "23ku", "rad": 5, "selected": "false", "loc": [52.2432674, 4.4494023]}, "22": {"name": ["Scholengemeenschap Pieter Zandt voor Lyceum Havo Mavo Vbo Lwoo"], "brinnr": "23vl", "rad": 5, "selected": "false", "loc": [52.6636792, 5.6290266]}, "340": {"name": ["Sint Ignatiusgymnasium"], "brinnr": "01et", "rad": 5, "selected": "false", "loc": [52.3499318, 4.8757435]}, "632": {"name": ["Het Rijnlands Lyc Scholengemeenschap Vwo Havo"], "brinnr": "16rh", "rad": 5, "selected": "false", "loc": [52.1819607, 4.4632361]}, "572": {"name": ["Atlas Onderwijsgroep voor gymnasium, atheneum, havo, vmbo"], "brinnr": "20cq", "rad": 5, "selected": "false", "loc": [52.0431337, 4.3130236]}, "634": {"name": ["St.- Jozefmavo"], "brinnr": "00vr", "rad": 5, "selected": "false", "loc": [51.9272208, 4.3423753]}, "12": {"name": ["Scholengemeenschap de Nieuwe Veste voor Lyceum Havo Mavo Vbo Lwoo"], "brinnr": "12ir", "rad": 5, "selected": "false", "loc": [52.6603042, 6.7523938]}, "187": {"name": ["Mundium College voor vwo, havo, mavo, vbo en lwoo"], "brinnr": "03xf", "rad": 5, "selected": "false", "loc": [51.1726601, 6.0022243]}, "648": {"name": ["Aloysiuscollege Katholiek Scholengemeenschap voor Vwo Havo en Mavo"], "brinnr": "01pu", "rad": 5, "selected": "false", "loc": [52.0939105, 4.3136112]}, "507": {"name": ["Agrarisch Opleidingen Centrum Holland Zeeland"], "brinnr": "11ul", "rad": 5, "selected": "false", "loc": [51.4976218, 3.891179999999999]}, "91": {"name": ["Gereformeerd Scholengemeenschap Guido De Bres Lyceum HAVO MAVO VBO LWOO"], "brinnr": "00jt", "rad": 5, "selected": "false", "loc": [52.0029951, 5.9429143]}, "163": {"name": ["Christelijkeschool voor praktijkonderwijs De Bolster"], "brinnr": "05op", "rad": 5, "selected": "false", "loc": [53.1968645, 6.564918]}, "464": {"name": ["Broeckland College voor Mavo Vbo Lwoo"], "brinnr": "23vd", "rad": 5, "selected": "false", "loc": [52.169453, 4.998675599999999]}, "16": {"name": ["Prof dr S Greijdanus College voor Vwo Havo Mavo Vbo Lwoo"], "brinnr": "17vs", "rad": 5, "selected": "false", "loc": [52.7012138, 6.1885159]}, "336": {"name": ["Sint-Vitusmavo"], "brinnr": "30jn", "rad": 5, "selected": "false", "loc": [52.2839311, 5.147884599999999]}, "530": {"name": ["Interconf Hofstadcollege voor LYC HAVO MAVO VBO LWOO"], "brinnr": "17hr", "rad": 5, "selected": "false", "loc": [52.063407, 4.2516602]}, "153": {"name": ["De Boog Christelijk School voor Prak Vorm"], "brinnr": "15dn", "rad": 5, "selected": "false", "loc": [52.1963602, 5.963949100000001]}, "453": {"name": ["Katholiek Scholengemeenschap De Breul voor Gymnasium Atheneum Havo en Mavo"], "brinnr": "00mk", "rad": 5, "selected": "false", "loc": [52.0764165, 5.2541857]}, "516": {"name": ["Accent Praktijkonderwijs Centrum"], "brinnr": "04ik", "rad": 5, "selected": "false", "loc": [51.9300529, 4.4752086]}, "221": {"name": ["Rooms Katholieke SGM Pius X voor Gymnasium Atheneum Havo Mavo Vbo Pro Lwoo"], "brinnr": "03kn", "rad": 5, "selected": "false", "loc": [51.3710278, 5.230436699999999]}, "502": {"name": ["PC RK SGM Zeldenrust Steelantcollege"], "brinnr": "00ly", "rad": 5, "selected": "false", "loc": [51.310429, 3.8563082]}, "462": {"name": ["Oosterlicht College PC SGM V ATH HAVO MAVO VBO"], "brinnr": "17gm", "rad": 5, "selected": "false", "loc": [52.0300307, 5.097886799999999]}, "262": {"name": ["Gymnasium Beekvliet"], "brinnr": "17jy", "rad": 5, "selected": "false", "loc": [51.64185029999999, 5.3633501]}, "118": {"name": ["Corlaer College"], "brinnr": "02dc", "rad": 5, "selected": "false", "loc": [52.2110478, 5.468431499999999]}, "368": {"name": ["IJburg College voor Vwo Havo Mavo en Vbo"], "brinnr": "28dh", "rad": 5, "selected": "false", "loc": [52.3516369, 5.0060414]}, "292": {"name": ["Newmancollege Rooms Katholieke Scholengemeenschap voor Vwo Havo Mavo"], "brinnr": "14sz", "rad": 5, "selected": "false", "loc": [51.6028356, 4.7879377]}, "583": {"name": ["Stedelijk Dalton Lyceum voor Lyceum Havo Mavo Vbo Lwoo"], "brinnr": "24py", "rad": 5, "selected": "false", "loc": [51.79239519999999, 4.685388]}, "559": {"name": ["Zuiderpark College voor Mavo Vbo en Lwoo"], "brinnr": "17yf", "rad": 5, "selected": "false", "loc": [51.8859985, 4.4946693]}, "554": {"name": ["Chr SGM op Ref Grondsl voor Pro, Lwoo, Vmbo, Havo en Vwo"], "brinnr": "02ea", "rad": 5, "selected": "false", "loc": [52.0195915, 4.7012064]}, "334": {"name": ["W De Zwijgercoll Chr SGM Vwo Havo op Chr Grndslg"], "brinnr": "02ev", "rad": 5, "selected": "false", "loc": [52.2768052, 5.1546331]}, "595": {"name": ["Lyceum Schravenlant voor Atheneum en Havo"], "brinnr": "16ei", "rad": 5, "selected": "false", "loc": [51.9252317, 4.391504299999999]}, "8": {"name": ["Hondsrug College Christelijke SGM voor LYC HAVO MAVO VBO LWOO"], "brinnr": "16vp", "rad": 5, "selected": "false", "loc": [52.7798046, 6.9048547]}, "573": {"name": ["School voor Speciaal Voortgezet Onderwijs De Einder"], "brinnr": "20kd", "rad": 5, "selected": "false", "loc": [52.0609411, 4.2951404]}, "613": {"name": ["Regionale Scholengemeenschap Goeree-Overflakkee voor Vwo Havo Mavo Vmbo"], "brinnr": "15qw", "rad": 5, "selected": "false", "loc": [51.7558741, 4.1626628]}, "242": {"name": ["Udens College voor Lyceum Havo Mavo Vbo Lwoo"], "brinnr": "06hf", "rad": 5, "selected": "false", "loc": [51.6641603, 5.6274644]}, "469": {"name": ["Protestants Christelijk Mavo Waldheim"], "brinnr": "00yo", "rad": 5, "selected": "false", "loc": [52.2051143, 5.2903893]}, "635": {"name": ["Fioretti College voor Gymnasium Atheneum Havo Mavo Vbo Lwoo"], "brinnr": "00uz", "rad": 5, "selected": "false", "loc": [52.2616702, 4.5679251]}, "399": {"name": ["SGM Kennemer Lyc Bz Sch Alg Grondsl v Vwo Havo"], "brinnr": "02gn", "rad": 5, "selected": "false", "loc": [52.39065069999999, 4.6212217]}, "597": {"name": ["Mavo Schravenlant XL voor mavo en vmbo"], "brinnr": "19km", "rad": 5, "selected": "false", "loc": [51.92022919999999, 4.3802028]}, "349": {"name": ["Kennemer Praktijkschool"], "brinnr": "28bn", "rad": 5, "selected": "false", "loc": [52.5040165, 4.6715252]}, "332": {"name": ["Clusius College Alkmaar"], "brinnr": "25ef", "rad": 5, "selected": "false", "loc": [52.6434063, 4.7572209]}, "476": {"name": ["Veenlanden College PC SGM v Mavo Havo Atheneum"], "brinnr": "05ra", "rad": 5, "selected": "false", "loc": [52.2151992, 4.8610682]}, "466": {"name": ["Seyster College voor Praktijkonderwijs"], "brinnr": "26hy", "rad": 5, "selected": "false", "loc": [52.0977571, 5.247259199999999]}, "232": {"name": ["ROC West-Brabant locatie Scala VMBO"], "brinnr": "25lx", "rad": 5, "selected": "false", "loc": [51.6024177, 4.815735399999999]}, "172": {"name": ["dr Aletta Jacobs College voor Lyc Havo Mavo Vbo Lwoo"], "brinnr": "25gm", "rad": 5, "selected": "false", "loc": [53.1533487, 6.7628353]}, "123": {"name": ["Christelijk Scholengemeenschap voor Atheneum Havo Mavo Vbo Lwoo"], "brinnr": "00tm", "rad": 5, "selected": "false", "loc": [51.9283063, 5.7232492]}, "86": {"name": ["Helicon Opleidingen"], "brinnr": "26cc", "rad": 5, "selected": "false", "loc": [51.9327662, 5.590831199999999]}, "542": {"name": ["Wartburg College Gereformeerde Scholengemeenschap voor Lyceum Havo Mavo Vbo Lwoo"], "brinnr": "00pg", "rad": 5, "selected": "false", "loc": [51.8839494, 4.5309595]}, "505": {"name": ["Praktijkschool Hulst"], "brinnr": "26jv", "rad": 5, "selected": "false", "loc": [51.2840549, 4.060734099999999]}, "286": {"name": ["Jan Tinbergen College Openbare Scholengemeenschap voor Ath Havo Mavo"], "brinnr": "19en", "rad": 5, "selected": "false", "loc": [51.5276612, 4.4826561]}, "576": {"name": ["Maerlant Lyceum met Afdeling Havo"], "brinnr": "20md", "rad": 5, "selected": "false", "loc": [52.0923436, 4.3236371]}, "538": {"name": ["Lentiz locatie Floracollege"], "brinnr": "14yd", "rad": 5, "selected": "false", "loc": [51.9892003, 4.2213904]}, "550": {"name": ["Groene Hart Praktijkschool"], "brinnr": "26lr", "rad": 5, "selected": "false", "loc": [52.1326377, 4.6538597]}, "570": {"name": ["Scholengemeenschap Haags Montessori Lyceum voor Lyceum Havo Mavo Vbo"], "brinnr": "02us", "rad": 5, "selected": "false", "loc": [52.0890206, 4.3167073]}, "319": {"name": ["De Viaan, school voor praktijkonderwijs"], "brinnr": "19yt", "rad": 5, "selected": "false", "loc": [52.6473139, 4.737933]}, "203": {"name": ["Raayland College RK SGM v Gymn Ath Havo Mavo Vmbo Pro"], "brinnr": "25fy", "rad": 5, "selected": "false", "loc": [51.51915899999999, 5.978991499999999]}, "210": {"name": ["Gymnasium voor het Bernardinuscollege"], "brinnr": "02zc", "rad": 5, "selected": "false", "loc": [50.8805691, 5.985134500000001]}, "398": {"name": ["Praktijkschool West-Friesland locatie Stede Broec"], "brinnr": "27pm", "rad": 5, "selected": "false", "loc": [52.69995429999999, 5.2156812]}, "182": {"name": ["DaCapo-College Einighauserweg"], "brinnr": "05gv", "rad": 5, "selected": "false", "loc": [50.9875073, 5.8253562]}, "278": {"name": ["Scholengemeenschap Were Di voor Lyc Havo Mavo Vbo Lwoo"], "brinnr": "21gv", "rad": 5, "selected": "false", "loc": [51.3610219, 5.4675178]}, "10": {"name": ["Stad & Esch Praktijkschool"], "brinnr": "19tq", "rad": 5, "selected": "false", "loc": [52.6916629, 6.1986968]}, "40": {"name": ["Emelwerda College Christelijke Scholengemeenschap voor Lwoo Mavo Havo Vwo"], "brinnr": "02jg", "rad": 5, "selected": "false", "loc": [52.7155884, 5.7511978]}, "124": {"name": ["Over Betuwe College voor Ath Havo Mavo Vbo Lwoo"], "brinnr": "17im", "rad": 5, "selected": "false", "loc": [51.893762, 5.9136583]}, "541": {"name": ["Carmelcollege Gouda voor tto gym ath havo mavo vmbo lwoo eoa"], "brinnr": "02lg", "rad": 5, "selected": "false", "loc": [52.0254494, 4.7135541]}, "590": {"name": ["De Goudse Scholengemeenschap voor VMBO-TL, HAVO en VWO Leo Vroman"], "brinnr": "13wh", "rad": 5, "selected": "false", "loc": [52.0209398, 4.7142765]}, "298": {"name": ["Scholengemeenschap De Overlaat Mavo Vbo Lwoo"], "brinnr": "05ax", "rad": 5, "selected": "false", "loc": [51.6848987, 5.0971324]}, "600": {"name": ["Scholengemeenschap Maerlant College voor Lyceum Havo Mavo Vbo Lwoo"], "brinnr": "11zh", "rad": 5, "selected": "false", "loc": [51.8932296, 4.1728686]}, "567": {"name": ["Veurs College Scholengemeenschap voor Atheneum Havo Mavo Vbo Lwoo"], "brinnr": "00xk", "rad": 5, "selected": "false", "loc": [52.0932389, 4.3916031]}, "250": {"name": ["Mollerlyceum Rooms Katholiek Scholengemeenschap voor Lyceum Havo Mavo Vbo Lwoo"], "brinnr": "02fy", "rad": 5, "selected": "false", "loc": [51.4991579, 4.2870047]}, "412": {"name": ["Kolom Praktijkcollege De Atlant"], "brinnr": "09py", "rad": 5, "selected": "false", "loc": [52.3262339, 4.8717115]}, "284": {"name": ["Jan van Brabant College vestiging Molenstraat"], "brinnr": "14lf", "rad": 5, "selected": "false", "loc": [51.4774283, 5.6662867]}, "177": {"name": ["Valuascollege Lyc Ath Havo Mavo Vbo Lwoo"], "brinnr": "01gn", "rad": 5, "selected": "false", "loc": [51.3750509, 6.1730515]}, "229": {"name": ["Praktijkschool Breda"], "brinnr": "15ny", "rad": 5, "selected": "false", "loc": [51.599456, 4.8034]}, "417": {"name": ["Atheneum College Hageveld"], "brinnr": "02uc", "rad": 5, "selected": "false", "loc": [52.3470057, 4.628777299999999]}, "299": {"name": ["Protestants Christelijke Scholengemeenschap Oude Hoven voor Lyceum Havo Mavo Vbo"], "brinnr": "00yh", "rad": 5, "selected": "false", "loc": [51.8174356, 4.954626999999999]}, "101": {"name": ["AOC Oost"], "brinnr": "01ic", "rad": 5, "selected": "false", "loc": [51.95378789999999, 6.3020914]}, "477": {"name": ["Meerwegen College"], "brinnr": "14rc", "rad": 5, "selected": "false", "loc": [52.16913049999999, 5.3869405]}, "231": {"name": ["AOC West Brabant, vestiging Prinsentuin Oudenbosch vmbo"], "brinnr": "21cy", "rad": 5, "selected": "false", "loc": [51.5921513, 4.537645599999999]}, "517": {"name": ["Accent Praktijkonderwijs Delfshaven"], "brinnr": "07hf", "rad": 5, "selected": "false", "loc": [51.9032534, 4.446682399999999]}, "603": {"name": ["Praktijk College Spijkenisse"], "brinnr": "18va", "rad": 5, "selected": "false", "loc": [51.84884599999999, 4.3132285]}, "472": {"name": ["de Passie, Evangelische School voor Vmbo-tl, Havo, Vwo"], "brinnr": "27dg", "rad": 5, "selected": "false", "loc": [52.0635267, 5.142951699999999]}, "5": {"name": ["Carmelcollege Emmen"], "brinnr": "00pf", "rad": 5, "selected": "false", "loc": [52.7782309, 6.9269754]}, "271": {"name": ["OMO Scholengroep Helmond"], "brinnr": "20jx", "rad": 5, "selected": "false", "loc": [51.4878994, 5.6570686]}, "460": {"name": ["Gerrit Rietveld College"], "brinnr": "14oy", "rad": 5, "selected": "false", "loc": [52.1091002, 5.1385676]}, "512": {"name": ["Ostrea Lyceum voor Lyceum Havo Mavo Vbo Lwoo"], "brinnr": "05oh", "rad": 5, "selected": "false", "loc": [51.5010863, 3.9012418]}, "275": {"name": ["OMO scholengroep Tongerlo voor LYC HAVO VMBO LWOO PRO"], "brinnr": "20zk", "rad": 5, "selected": "false", "loc": [51.526464, 4.4581249]}, "497": {"name": ["De Baanbreker, school voor praktijkonderwijs"], "brinnr": "07bm", "rad": 5, "selected": "false", "loc": [52.0174938, 5.050701099999999]}, "478": {"name": ["Accent Praktijkonderwijs"], "brinnr": "28ca", "rad": 5, "selected": "false", "loc": [52.16436479999999, 5.4093389]}, "62": {"name": ["Regionale Scholengemeenschap Magister Alvinus voor Vwo Havo Mavo Vbo"], "brinnr": "16fp", "rad": 5, "selected": "false", "loc": [53.0303078, 5.6539598]}, "82": {"name": ["Regionale Scholengemeenschap Pantarijn voor Lyc Havo Mavo Vbo Pro Lwoo"], "brinnr": "16yv", "rad": 5, "selected": "false", "loc": [51.9795589, 5.675665299999999]}, "577": {"name": ["Dalton Den Haag gymnasium atheneum havo"], "brinnr": "20mf", "rad": 5, "selected": "false", "loc": [52.06689369999999, 4.2377304]}, "585": {"name": ["Algemeen Bijzondere School voor Praktijkonderwijs De Sprong"], "brinnr": "26hd", "rad": 5, "selected": "false", "loc": [51.825605, 4.7568112]}, "330": {"name": ["Het 4e Gymnasium"], "brinnr": "30gc", "rad": 5, "selected": "false", "loc": [52.3929756, 4.8799525]}, "431": {"name": ["Agrarisch Opleidingen Centrum De Groene Welle"], "brinnr": "13us", "rad": 5, "selected": "false", "loc": [52.5029404, 6.0878204]}, "378": {"name": ["Coornhertlyc Gem Scholengemeenschap Lyceum Havo Mavo"], "brinnr": "20rf", "rad": 5, "selected": "false", "loc": [52.36212330000001, 4.6145651]}, "633": {"name": ["Scholengemeenschap Montessori Lyceum Rotterdam voor Gymnasium Atheneum en Havo"], "brinnr": "02gs", "rad": 5, "selected": "false", "loc": [51.92522200000001, 4.4606997]}, "97": {"name": ["Koningin Wilhelmina College voor Lyc Havo Mavo Vbo Pro en Lwoo"], "brinnr": "19qa", "rad": 5, "selected": "false", "loc": [51.9516082, 5.2347604]}, "224": {"name": ["Vakcollege Tilburg, sectoren Zorg & Welzijn en Techniek"], "brinnr": "02is", "rad": 5, "selected": "false", "loc": [51.5694813, 5.0623773]}, "145": {"name": ["Rietveld Lyceum Scholengemeenschap voor Gymn Ath Havo Mavo"], "brinnr": "20ad", "rad": 5, "selected": "false", "loc": [51.9806888, 6.289130399999999]}, "370": {"name": ["Montessori College voor Mavo Aerdenhout"], "brinnr": "02yh", "rad": 5, "selected": "false", "loc": [52.3555058, 4.5932032]}, "119": {"name": ["Accent Praktijkonderwijs"], "brinnr": "26hu", "rad": 5, "selected": "false", "loc": [52.2110478, 5.468431499999999]}, "524": {"name": ["Accent Praktijkonderwijs Capelle"], "brinnr": "26hr", "rad": 5, "selected": "false", "loc": [51.9576441, 4.5851554]}, "239": {"name": ["Lorentz Casimir Lyceum"], "brinnr": "25kx", "rad": 5, "selected": "false", "loc": [51.4488747, 5.5089026]}, "35": {"name": ["Openbare Scholengemeenschap Echnaton"], "brinnr": "16aw", "rad": 5, "selected": "false", "loc": [52.3677755, 5.2123855]}, "134": {"name": ["Cambium College voor Atheneum Havo Mavo Vbo Lwoo"], "brinnr": "17ay", "rad": 5, "selected": "false", "loc": [51.8034007, 5.232448499999999]}, "342": {"name": ["Scholengemeenschap Sint Nicolaas Lyceum voor Lyceum en Havo"], "brinnr": "14se", "rad": 5, "selected": "false", "loc": [52.34085049999999, 4.8772337]}, "24": {"name": ["Berechja College voor MAVO HAVO VBO"], "brinnr": "18xx", "rad": 5, "selected": "false", "loc": [52.6688793, 5.6053267]}, "402": {"name": ["Stichting Media Amsterdam"], "brinnr": "02pa", "rad": 5, "selected": "false", "loc": [52.3945395, 4.8549174]}, "454": {"name": ["College De Heemlanden SGM voor Mavo Havo Atheneum"], "brinnr": "22ne", "rad": 5, "selected": "false", "loc": [52.0333081, 5.167164]}, "240": {"name": ["Praktijkschool De Zwaaikom"], "brinnr": "13vv", "rad": 5, "selected": "false", "loc": [51.6419213, 4.8462467]}, "259": {"name": ["2College voor Lyceum Havo Mavo Vbo"], "brinnr": "16ox", "rad": 5, "selected": "false", "loc": [51.5769432, 5.1848797]}, "363": {"name": ["Dalton Scholengemeenschap Spinozalyceum voor Vwo Havo Mavo"], "brinnr": "21bh", "rad": 5, "selected": "false", "loc": [52.3424566, 4.8667602]}, "142": {"name": ["Praktijkonderwijs Zutphen"], "brinnr": "13eb", "rad": 5, "selected": "false", "loc": [52.1391143, 6.2110398]}, "391": {"name": ["Pascal College  voor Vwo Havo Mavo Vbo Lwoo"], "brinnr": "02vq", "rad": 5, "selected": "false", "loc": [52.4547312, 4.8306949]}, "151": {"name": ["Christelijk College Groevenbeek"], "brinnr": "00wi", "rad": 5, "selected": "false", "loc": [52.2910187, 5.623016]}, "155": {"name": ["Baudartius College Chr SGM voor Mavo- Havo- Atheneum- Gymnasium"], "brinnr": "02vs", "rad": 5, "selected": "false", "loc": [52.1438242, 6.2004489]}, "345": {"name": ["Scholen aan Zee 1"], "brinnr": "21vb", "rad": 5, "selected": "false", "loc": [52.940269, 4.750138]}, "64": {"name": ["Noordzee Onderwijs Groep- locatie Maritieme Academie Harlingen"], "brinnr": "01kl", "rad": 5, "selected": "false", "loc": [53.1726115, 5.4345082]}, "611": {"name": ["Erasmianum Gemeente Gymnasium"], "brinnr": "15sc", "rad": 5, "selected": "false", "loc": [51.9124363, 4.4689562]}, "622": {"name": ["Regionale Scholengemeenschap Hoeksche Waard"], "brinnr": "15xv", "rad": 5, "selected": "false", "loc": [51.82072340000001, 4.3959963]}, "168": {"name": ["Reitdiepcollege voor Atheneum Havo Mavo Vbo Lwoo"], "brinnr": "13zu", "rad": 5, "selected": "false", "loc": [53.2325561, 6.5515262]}, "624": {"name": ["Het Schoonhovens College"], "brinnr": "15om", "rad": 5, "selected": "false", "loc": [51.9517628, 4.844857]}, "209": {"name": ["School voor Praktijk onderwijs t Wildveld"], "brinnr": "17ux", "rad": 5, "selected": "false", "loc": [51.3605635, 6.163598100000001]}, "141": {"name": ["Ludger College voor Lyceum Havo Mavo Vbo Lwoo"], "brinnr": "02nz", "rad": 5, "selected": "false", "loc": [51.9707669, 6.3024318]}, "587": {"name": ["School voor Praktijkonderwijs Het Atrium"], "brinnr": "21km", "rad": 5, "selected": "false", "loc": [52.0504066, 4.4899824]}, "126": {"name": ["De Meerwaarde Praktijkonderwijs"], "brinnr": "02fo", "rad": 5, "selected": "false", "loc": [52.1318699, 5.6015137]}, "359": {"name": ["Scholengemeenschap voor Athenum en Havo Het Hervormd Lyceum Zuid"], "brinnr": "02ar", "rad": 5, "selected": "false", "loc": [52.34834559999999, 4.8781383]}, "377": {"name": ["Gem Schoter Scholengemeenschap voor Atheneum Havo en Mavo"], "brinnr": "20rc", "rad": 5, "selected": "false", "loc": [52.4103911, 4.6470674]}, "461": {"name": ["Christelijk Gymnasium"], "brinnr": "16pa", "rad": 5, "selected": "false", "loc": [52.0875935, 5.0993851]}, "521": {"name": ["Comenius College Christelijke Scholengemeenschap voor vwo havo vmbo lwoo"], "brinnr": "19gy", "rad": 5, "selected": "false", "loc": [51.9294732, 4.5833724]}, "129": {"name": ["Mijnschool voor Praktijkonderwijs"], "brinnr": "07yu", "rad": 5, "selected": "false", "loc": [52.3446282, 5.6161365]}, "252": {"name": ["Voortgezet Onderwijs Veghel"], "brinnr": "04su", "rad": 5, "selected": "false", "loc": [51.62861119999999, 5.540176499999999]}, "636": {"name": ["Teylingen College voor Gymnasium Atheneum Havo Mavo Vbo Lwoo"], "brinnr": "02kb", "rad": 5, "selected": "false", "loc": [52.22272640000001, 4.4750184]}, "630": {"name": ["Het Rijnlands Lyceum Scholengemeenschap voor Havo VWO"], "brinnr": "02gp", "rad": 5, "selected": "false", "loc": [52.13232989999999, 4.3875281]}, "103": {"name": ["Pro College Nijmegen/Bemmel voor Praktijkonderwijs"], "brinnr": "26jr", "rad": 5, "selected": "false", "loc": [51.8332454, 5.823333]}, "430": {"name": ["Twickel Scholengemeenschap voor ATH HAVO MAVO VBO"], "brinnr": "19hg", "rad": 5, "selected": "false", "loc": [52.2945699, 6.7581226]}, "501": {"name": ["NEHALENNIA Stedelijke Scholengemeenschap voor LYC HAVO MAVO VBO LWOO"], "brinnr": "20cp", "rad": 5, "selected": "false", "loc": [51.4925074, 3.594580299999999]}, "450": {"name": ["School voor Praktijkonderwijs De Maat"], "brinnr": "03zy", "rad": 5, "selected": "false", "loc": [52.5226767, 6.417531299999999]}, "533": {"name": ["Scholengemeenschap Spieringshoek voor Gymnasium Atheneum en HAVO"], "brinnr": "00jr", "rad": 5, "selected": "false", "loc": [51.9189247, 4.3784611]}, "514": {"name": ["Calvijn College voor Reformatorisch Vmbo Havo Vwo"], "brinnr": "03jy", "rad": 5, "selected": "false", "loc": [51.5068764, 3.879157]}, "582": {"name": ["De Noordhoek"], "brinnr": "26mp", "rad": 5, "selected": "false", "loc": [51.8478274, 4.9717034]}, "301": {"name": ["St Willibrord Gymnasium"], "brinnr": "02qp", "rad": 5, "selected": "false", "loc": [51.44743829999999, 5.7823804]}, "491": {"name": ["De Baander"], "brinnr": "03sx", "rad": 5, "selected": "false", "loc": [52.1644643, 5.4053565]}, "173": {"name": ["Praktijkonderwijs Eemsdeltacollege"], "brinnr": "30jm", "rad": 5, "selected": "false", "loc": [53.3149764, 6.8754993]}, "25": {"name": ["Groenhorst College voor Praktijkonderwijs"], "brinnr": "05nv", "rad": 5, "selected": "false", "loc": [52.7106466, 5.739957]}, "588": {"name": ["Scholen Combinatie Zoetermeer - Picasso Lyceum"], "brinnr": "25ga", "rad": 5, "selected": "false", "loc": [52.0429691, 4.4967128]}, "439": {"name": ["Regionale Scholengemeenschap Tromp Meesters voor Lyc Havo Mavo Vbo Lwoo"], "brinnr": "16gz", "rad": 5, "selected": "false", "loc": [52.7817532, 6.1129155]}, "114": {"name": ["Stedelijk Gymnasium Nijmegen"], "brinnr": "20ci", "rad": 5, "selected": "false", "loc": [51.84618, 5.85625]}, "227": {"name": ["Steenspil  VMBO"], "brinnr": "02hi", "rad": 5, "selected": "false", "loc": [51.5404765, 4.2912681]}, "31": {"name": ["Ichthus College Scholengemeenschap voor Lyceum Havo Mavo Vbo Lwoo"], "brinnr": "02vb", "rad": 5, "selected": "false", "loc": [52.5219269, 5.7119725]}, "244": {"name": ["Stg ROC Summa College"], "brinnr": "25mb", "rad": 5, "selected": "false", "loc": [51.4670029, 5.497402399999999]}, "396": {"name": ["De Faam voor Praktijkonderwijs"], "brinnr": "26jz", "rad": 5, "selected": "false", "loc": [52.46155090000001, 4.8171354]}, "626": {"name": ["Christelijke Scholengemeenschap voor Atheneum Havo Mavo Vbo Lwoo Prins Maurits"], "brinnr": "03rb", "rad": 5, "selected": "false", "loc": [51.7558741, 4.1626628]}, "419": {"name": ["Mendel College Interconfessionele Scholengemeenschap Voor Mavo Havo Vwo"], "brinnr": "07fh", "rad": 5, "selected": "false", "loc": [52.40708739999999, 4.631382800000001]}, "125": {"name": ["De Meerwaarde"], "brinnr": "01mu", "rad": 5, "selected": "false", "loc": [52.1318699, 5.6015137]}, "411": {"name": ["Kolom Praktijkcollege De Schakel"], "brinnr": "01kd", "rad": 5, "selected": "false", "loc": [52.38639149999999, 4.6289639]}, "404": {"name": ["Keizer Karel College Vwo Havo"], "brinnr": "02qz", "rad": 5, "selected": "false", "loc": [52.30178739999999, 4.8495554]}, "580": {"name": ["Merewade College Openbare Scholengemeenschap voor Ath Havo Mavo Vbo Lwoo"], "brinnr": "24tp", "rad": 5, "selected": "false", "loc": [51.82988479999999, 4.987432699999999]}, "300": {"name": ["Sint Oelbert Gymnasium"], "brinnr": "02qo", "rad": 5, "selected": "false", "loc": [51.6298661, 4.8478392]}, "191": {"name": ["Elzendaalcollege Rooms Katholieke Scholengemeenschap voor Lyc Havo Mavo"], "brinnr": "17hn", "rad": 5, "selected": "false", "loc": [51.6861206, 5.989201800000001]}, "108": {"name": ["Canisius College Lyceum Havo Mavo Vbo Lwoo"], "brinnr": "01vn", "rad": 5, "selected": "false", "loc": [51.837817, 5.8844195]}, "213": {"name": ["Charlemagne College voor VWO (ath.-gymn.), havo, vmbo, vmbo-t, lwoo"], "brinnr": "17jb", "rad": 5, "selected": "false", "loc": [50.8978771, 6.0243061]}, "592": {"name": ["Het Segment Regionale School voor Praktijkonderwijs"], "brinnr": "26lt", "rad": 5, "selected": "false", "loc": [52.0148667, 4.7026666]}, "574": {"name": ["Gymnasium Haganum"], "brinnr": "20lu", "rad": 5, "selected": "false", "loc": [52.0824286, 4.2890023]}, "609": {"name": ["Thorbecke Voortgezet Onderwijs voor Atheneum Havo Mavo Vbo Lwoo"], "brinnr": "15hx", "rad": 5, "selected": "false", "loc": [51.9390333, 4.5474045]}, "535": {"name": ["Christelijke Scholengemeenschap De Lage Waard voor Ath Havo Mavo Vbo Lwoo"], "brinnr": "16qa", "rad": 5, "selected": "false", "loc": [51.8427247, 4.6914125]}, "52": {"name": ["De Diken - locatie de Zuiderpoort"], "brinnr": "04fr", "rad": 5, "selected": "false", "loc": [53.0322001, 5.645537099999999]}, "386": {"name": ["Regius College Schagen voor Gym, Ath, Havo, Vmbo tl, Vmbo basis/kader"], "brinnr": "16cx", "rad": 5, "selected": "false", "loc": [52.7830558, 4.7974366]}, "480": {"name": ["Utrechts Stedelijk Gymnasium"], "brinnr": "15jm", "rad": 5, "selected": "false", "loc": [52.0812306, 5.1333633]}, "649": {"name": ["Christelijk Lyceum Delft Scholengemeenschap voor Lyceum Havo Mavo Vbo"], "brinnr": "01gx", "rad": 5, "selected": "false", "loc": [52.0063041, 4.341963499999999]}, "618": {"name": ["Emmauscollege Rooms Katholieke Scholengemeenschap voor Vwo en Havo"], "brinnr": "08cu", "rad": 5, "selected": "false", "loc": [51.94834609999999, 4.5644803]}, "321": {"name": ["Huygens College Heerhugowaard voor vwo havo mavo en vbo"], "brinnr": "19zx", "rad": 5, "selected": "false", "loc": [52.6610192, 4.8323828]}, "628": {"name": ["Onderwijsgr. Zuid-Hollandse Waarden gymnasium, atheneum, havo, mavo, vmbo, lwoo"], "brinnr": "18tr", "rad": 5, "selected": "false", "loc": [51.88479719999999, 4.6036081]}, "98": {"name": ["Christelijk College De Noordgouw"], "brinnr": "00mp", "rad": 5, "selected": "false", "loc": [52.3775142, 6.02814]}, "270": {"name": ["Eckartcollege voor Lyc Havo Mavo Vbo Lwoo"], "brinnr": "20ib", "rad": 5, "selected": "false", "loc": [51.4653999, 5.4985731]}, "616": {"name": ["Leonardo College voor Atheneum Havo Mavo"], "brinnr": "20cl", "rad": 5, "selected": "false", "loc": [52.1520107, 4.469984]}, "508": {"name": ["Het Bolwerk"], "brinnr": "01hq", "rad": 5, "selected": "false", "loc": [51.4869493, 3.6097639]}, "179": {"name": ["Blariacumcollege Scholengemeenschap voor Lyceum Havo Mavo Vbo Lwoo"], "brinnr": "19hr", "rad": 5, "selected": "false", "loc": [51.3736253, 6.140619399999999]}, "645": {"name": ["Ashram College Rooms Katholieke Scholengemeenschap voor Atheneum Havo Mavo Vbo"], "brinnr": "04df", "rad": 5, "selected": "false", "loc": [52.1465543, 4.6547712]}, "15": {"name": ["Zernike College voor Ath Havo Mavo Vbo"], "brinnr": "20er", "rad": 5, "selected": "false", "loc": [53.0943154, 6.6761542]}, "484": {"name": ["UniC school voor vwo en havo"], "brinnr": "30ub", "rad": 5, "selected": "false", "loc": [52.0779619, 5.098008999999999]}, "314": {"name": ["Vossius Gymnasium"], "brinnr": "21af", "rad": 5, "selected": "false", "loc": [52.34550840000001, 4.8843079]}, "316": {"name": ["Focus school voor praktijkonderwijs"], "brinnr": "08uv", "rad": 5, "selected": "false", "loc": [52.67101109999999, 4.8274192]}, "625": {"name": ["Coenecoop College voor Atheneum Havo Mavo Voorbereidend Beroeps Onderwijs"], "brinnr": "00bd", "rad": 5, "selected": "false", "loc": [52.03961109999999, 4.6514359]}, "447": {"name": ["Praktijkschool Het Kwartiers"], "brinnr": "19uo", "rad": 5, "selected": "false", "loc": [52.51478059999999, 6.0652308]}, "29": {"name": ["St Bonifatius Mavo"], "brinnr": "02kr", "rad": 5, "selected": "false", "loc": [52.7127376, 5.7559242]}, "532": {"name": ["Interconfessionele Scholengroep Westland voor Lyceum Havo Mavo Vbo Lwoo"], "brinnr": "21hc", "rad": 5, "selected": "false", "loc": [51.987213, 4.2045812]}, "36": {"name": ["Openbare Scholengemeenschap De Meergronden voor Lyc Havo Mavo Vbo Lwoo"], "brinnr": "17dn", "rad": 5, "selected": "false", "loc": [52.3362103, 5.217670099999999]}, "425": {"name": ["Carmel College Salland Katholieke Scholengemeenschap"], "brinnr": "04oy", "rad": 5, "selected": "false", "loc": [52.391461, 6.2685767]}, "162": {"name": ["Christelijke Scholengemeenschap Groningen Vmbo Havo Atheneum"], "brinnr": "14rp", "rad": 5, "selected": "false", "loc": [53.23914509999999, 6.5808827]}, "474": {"name": ["Openbaar lyceum De Amersfoortse Berg"], "brinnr": "20ea", "rad": 5, "selected": "false", "loc": [52.1419833, 5.371000899999999]}, "551": {"name": ["Andreas College Christelijke Scholengemeenschap voor VWO Havo Vmbo"], "brinnr": "25gd", "rad": 5, "selected": "false", "loc": [52.1967651, 4.4166668]}, "395": {"name": ["Scholengemeenschap ZAAM zuid voor Vwo Havo Mavo Vbo Lwoo"], "brinnr": "21et", "rad": 5, "selected": "false", "loc": [52.3489649, 4.8747067]}, "328": {"name": ["De Pijler school voor praktijk onderwijs"], "brinnr": "26jy", "rad": 5, "selected": "false", "loc": [52.940269, 4.750138]}, "445": {"name": ["OSG Hengelo voor LYC HAVO MAVO VBO LWOO"], "brinnr": "20cs", "rad": 5, "selected": "false", "loc": [52.275357, 6.7941777]}, "144": {"name": ["Gerrit Komrij College Gemeentelijke Scholengemeenschap voor Vwo Havo Vmbo"], "brinnr": "17aa", "rad": 5, "selected": "false", "loc": [51.9655145, 6.715499299999999]}, "175": {"name": ["CITAVERDE College"], "brinnr": "21cs", "rad": 5, "selected": "false", "loc": [51.4311236, 6.025899799999999]}, "68": {"name": ["Burg Harmsma SGM voor VO Mavo Lhno en Lto"], "brinnr": "01wm", "rad": 5, "selected": "false", "loc": [53.00376199999999, 6.0648636]}, "51": {"name": ["Scholengemeenschap Gaasterland voor Christelijk Mavo en Lhno"], "brinnr": "00zh", "rad": 5, "selected": "false", "loc": [52.8941246, 5.5805056]}, "339": {"name": ["Gooise Scholen Federatie Weesp"], "brinnr": "24tg", "rad": 5, "selected": "false", "loc": [52.3102874, 5.0275677]}, "197": {"name": ["Scholengemeenschap Philips van Horne voor LYC HAVO MAVO VBO LWOO"], "brinnr": "18dd", "rad": 5, "selected": "false", "loc": [51.2562777, 5.7182973]}, "236": {"name": ["Augustinianum Scholengemeenschap voor Vwo en Havo"], "brinnr": "01fy", "rad": 5, "selected": "false", "loc": [51.4333286, 5.4963206]}, "459": {"name": ["Niftarlake College Christelijke Scholengemeenschap voor Atheneum Havo Mavo"], "brinnr": "03oy", "rad": 5, "selected": "false", "loc": [52.1357689, 5.0210402]}, "302": {"name": ["Praktijkcollege Tilburg"], "brinnr": "12pr", "rad": 5, "selected": "false", "loc": [51.5784126, 5.098711199999999]}, "267": {"name": ["Scholengroep Het Plein voor Ath Gym Havo Mavo Vbo Pro en Lwoo"], "brinnr": "20at", "rad": 5, "selected": "false", "loc": [51.414075, 5.4911436]}, "352": {"name": ["Herbert Vissers College Christelijke Scholengemeenschap voor Lyceu Havo Mavo Vbo"], "brinnr": "03ru", "rad": 5, "selected": "false", "loc": [52.2726199, 4.6387258]}, "156": {"name": ["Jacobus Fruijtier Scholengemeenschap v Lyceum Havo Mavo Vbo Lwoo"], "brinnr": "01rl", "rad": 5, "selected": "false", "loc": [52.2350199, 5.9650967]}, "369": {"name": ["Haarlem College Scholengemeenschap voor Mavo Vbo Lwoo"], "brinnr": "02km", "rad": 5, "selected": "false", "loc": [52.3691227, 4.6509845]}, "305": {"name": ["Markland College Oudenbosch Katholieke SGM voor Gymn Ath Havo Mavo Vmbo Pro"], "brinnr": "06xl", "rad": 5, "selected": "false", "loc": [51.5854466, 4.5416525]}, "408": {"name": ["Trinitas College RK scholengemeenschap voor ATHENEUM, HAVO, MAVO, VBO, LWOO"], "brinnr": "00xa", "rad": 5, "selected": "false", "loc": [52.6629808, 4.8503425]}, "392": {"name": ["Scholengemeenschap ZAAM Oost voor Vwo  Havo Mavo Vbo Lwoo"], "brinnr": "14rf", "rad": 5, "selected": "false", "loc": [52.3498762, 4.9254964]}, "547": {"name": ["Christelijke Scholengemeenschap Willem van Oranje voor ATH HAVO MAVO"], "brinnr": "08vu", "rad": 5, "selected": "false", "loc": [51.8225249, 4.3897837]}, "540": {"name": ["Christelijk Gymnasium Sorghvliet"], "brinnr": "02dq", "rad": 5, "selected": "false", "loc": [52.0914975, 4.2837989]}, "489": {"name": ["Regionale Scholengemeenschap Broklede voor Atheneum en Havo"], "brinnr": "11ny", "rad": 5, "selected": "false", "loc": [52.1792366, 4.9966042]}, "414": {"name": ["Kolom Praktijkcollege Noord"], "brinnr": "26hp", "rad": 5, "selected": "false", "loc": [52.41988019999999, 4.8800593]}, "629": {"name": ["Gereformeerde Scholengemeenschap Randstad Gymnasium Atheneum HAVO VMBO"], "brinnr": "00tu", "rad": 5, "selected": "false", "loc": [51.9450466, 4.5606272]}, "444": {"name": ["De Wissel Ml Vbo"], "brinnr": "19ng", "rad": 5, "selected": "false", "loc": [52.2143345, 6.8612661]}, "557": {"name": ["Het Lyceum Rotterdam voor Vwo en Havo"], "brinnr": "05xj", "rad": 5, "selected": "false", "loc": [51.9218017, 4.459268799999999]}, "7": {"name": ["Roelof van Echten College"], "brinnr": "02va", "rad": 5, "selected": "false", "loc": [52.7222182, 6.4955656]}, "586": {"name": ["Hans Petri School"], "brinnr": "27vf", "rad": 5, "selected": "false", "loc": [51.79789719999999, 4.6685788]}, "199": {"name": ["Graaf Huyn College voor LYC HAVO MAVO VBO LWOO"], "brinnr": "19pv", "rad": 5, "selected": "false", "loc": [50.9576027, 5.8250904]}, "282": {"name": ["De Rijzert, school voor Praktijkonderwijs"], "brinnr": "17ma", "rad": 5, "selected": "false", "loc": [51.7023845, 5.2663309]}}